{"7":[{"text":"beloved","number":"27"},{"text":"hear","number":"191"},{"text":"him","number":"846"},{"text":"them","number":"846"},{"text":"there was","number":"1096"},{"text":"out of","number":"1537"},{"text":"that overshadowed","number":"1982"},{"text":"came","number":"2064"},{"text":"is","number":"2076"},{"text":"And","number":"2532"},{"text":"and","number":"2532"},{"text":"saying","number":"3004"},{"text":"my","number":"3450"},{"text":"a cloud","number":"3507"},{"text":"the cloud","number":"3507"},{"text":"This","number":"3778"},{"text":"Son","number":"5207"},{"text":"a voice","number":"5456"}],"32":[{"text":"they understood not","number":"50"},{"text":"him","number":"846"},{"text":"But","number":"1161"},{"text":"to ask","number":"1905"},{"text":"and","number":"2532"},{"text":"that saying","number":"4487"},{"text":"were afraid","number":"5399"}],"25":[{"text":"the foul","number":"169"},{"text":"Thou dumb","number":"216"},{"text":"him","number":"846"},{"text":"him","number":"846"},{"text":"unto him","number":"846"},{"text":"When","number":"1161"},{"text":"I","number":"1473"},{"text":"saw","number":"1492"},{"text":"into","number":"1519"},{"text":"enter","number":"1525"},{"text":"out of","number":"1537"},{"text":"come","number":"1831"},{"text":"came running together","number":"1998"},{"text":"charge","number":"2004"},{"text":"he rebuked","number":"2008"},{"text":"Jesus","number":"2424"},{"text":"and","number":"2532"},{"text":"and","number":"2532"},{"text":"deaf","number":"2974"},{"text":"saying","number":"3004"},{"text":"no more","number":"3371"},{"text":"that","number":"3754"},{"text":"the people","number":"3793"},{"text":"spirit","number":"4151"},{"text":"spirit","number":"4151"},{"text":"thee","number":"4671"}],"38":[{"text":"he followeth","number":"190"},{"text":"he followeth","number":"190"},{"text":"answered","number":"611"},{"text":"him","number":"846"},{"text":"him","number":"846"},{"text":"devils","number":"1140"},{"text":"And","number":"1161"},{"text":"Master","number":"1320"},{"text":"we saw","number":"1492"},{"text":"casting out","number":"1544"},{"text":"us","number":"2254"},{"text":"us","number":"2254"},{"text":"John","number":"2491"},{"text":"and","number":"2532"},{"text":"we forbad","number":"2967"},{"text":"saying","number":"3004"},{"text":"name","number":"3686"},{"text":"and","number":"3739"},{"text":"because","number":"3754"},{"text":"not","number":"3756"},{"text":"not","number":"3756"},{"text":"in thy","number":"4675"},{"text":"one","number":"5100"}],"17":[{"text":"a dumb","number":"216"},{"text":"answered","number":"611"},{"text":"Master","number":"1320"},{"text":"one","number":"1520"},{"text":"of","number":"1537"},{"text":"and said","number":"2036"},{"text":"which hath","number":"2192"},{"text":"And","number":"2532"},{"text":"my","number":"3450"},{"text":"the multitude","number":"3793"},{"text":"spirit","number":"4151"},{"text":"unto","number":"4314"},{"text":"thee","number":"4571"},{"text":"son","number":"5207"},{"text":"I have brought","number":"5342"}],"50":[{"text":"Salt","number":"217"},{"text":"salt","number":"217"},{"text":"the salt","number":"217"},{"text":"another","number":"240"},{"text":"one","number":"240"},{"text":"his saltness","number":"358"},{"text":"will ye season","number":"741"},{"text":"it","number":"846"},{"text":"have lost","number":"1096"},{"text":"but","number":"1161"},{"text":"if","number":"1437"},{"text":"yourselves","number":"1438"},{"text":"have peace","number":"1514"},{"text":"in","number":"1722"},{"text":"wherewith","number":"1722"},{"text":"with","number":"1722"},{"text":"Have","number":"2192"},{"text":"and","number":"2532"},{"text":"is good","number":"2570"}],"49":[{"text":"shall be salted","number":"233"},{"text":"shall be salted","number":"233"},{"text":"with salt","number":"251"},{"text":"For","number":"1063"},{"text":"sacrifice","number":"2378"},{"text":"and","number":"2532"},{"text":"every","number":"3956"},{"text":"every one","number":"3956"},{"text":"with fire","number":"4442"}],"13":[{"text":"But","number":"235"},{"text":"him","number":"846"},{"text":"unto him","number":"846"},{"text":"it is written","number":"1125"},{"text":"of","number":"1909"},{"text":"come","number":"2064"},{"text":"is","number":"2064"},{"text":"Elias","number":"2243"},{"text":"they listed","number":"2309"},{"text":"as","number":"2531"},{"text":"and","number":"2532"},{"text":"indeed","number":"2532"},{"text":"I say","number":"3004"},{"text":"whatsoever","number":"3745"},{"text":"That","number":"3754"},{"text":"they have done","number":"4160"},{"text":"unto you","number":"5213"}],"22":[{"text":"but","number":"235"},{"text":"destroy","number":"622"},{"text":"him","number":"846"},{"text":"him","number":"846"},{"text":"it hath cast","number":"906"},{"text":"and help","number":"997"},{"text":"thou canst","number":"1410"},{"text":"into","number":"1519"},{"text":"do any thing","number":"1536"},{"text":"if","number":"1536"},{"text":"on","number":"1909"},{"text":"us","number":"2248"},{"text":"us","number":"2254"},{"text":"to","number":"2443"},{"text":"And","number":"2532"},{"text":"and","number":"2532"},{"text":"into","number":"2532"},{"text":"ofttimes","number":"4178"},{"text":"the fire","number":"4442"},{"text":"have compassion","number":"4697"},{"text":"the waters","number":"5204"}],"37":[{"text":"but","number":"235"},{"text":"him that sent","number":"649"},{"text":"receiveth","number":"1209"},{"text":"receiveth","number":"1209"},{"text":"shall receive","number":"1209"},{"text":"shall receive","number":"1209"},{"text":"one","number":"1520"},{"text":"me","number":"1691"},{"text":"me","number":"1691"},{"text":"me","number":"1691"},{"text":"in","number":"1909"},{"text":"and","number":"2532"},{"text":"me","number":"3165"},{"text":"my","number":"3450"},{"text":"name","number":"3686"},{"text":"Whosoever","number":"3739"},{"text":"whosoever","number":"3739"},{"text":"not","number":"3756"},{"text":"children","number":"3813"},{"text":"of such","number":"5108"}],"8":[{"text":"save","number":"235"},{"text":"themselves","number":"1438"},{"text":"they saw","number":"1492"},{"text":"suddenly","number":"1819"},{"text":"Jesus","number":"2424"},{"text":"And","number":"2532"},{"text":"with","number":"3326"},{"text":"only","number":"3441"},{"text":"no man","number":"3762"},{"text":"any more","number":"3765"},{"text":"when they had looked round about","number":"4017"}],"34":[{"text":"themselves","number":"240"},{"text":"for","number":"1063"},{"text":"But","number":"1161"},{"text":"they had disputed","number":"1256"},{"text":"by","number":"1722"},{"text":"should be the greatest","number":"3187"},{"text":"the way","number":"3598"},{"text":"among","number":"4314"},{"text":"they held their peace","number":"4623"},{"text":"who","number":"5101"}],"1":[{"text":"Verily","number":"281"},{"text":"unto them","number":"846"},{"text":"the kingdom","number":"932"},{"text":"shall","number":"1089"},{"text":"taste","number":"1089"},{"text":"power","number":"1411"},{"text":"they have seen","number":"1492"},{"text":"there be","number":"1526"},{"text":"with","number":"1722"},{"text":"come","number":"2064"},{"text":"till","number":"2193"},{"text":"of death","number":"2288"},{"text":"of God","number":"2316"},{"text":"of them that stand","number":"2476"},{"text":"And","number":"2532"},{"text":"I say","number":"3004"},{"text":"he said","number":"3004"},{"text":"not","number":"3364"},{"text":"which","number":"3748"},{"text":"That","number":"3754"},{"text":"some","number":"5100"},{"text":"unto you","number":"5213"},{"text":"here","number":"5602"}],"41":[{"text":"verily","number":"281"},{"text":"he shall","number":"622"},{"text":"lose","number":"622"},{"text":"his","number":"848"},{"text":"For","number":"1063"},{"text":"in","number":"1722"},{"text":"ye belong","number":"2075"},{"text":"I say","number":"3004"},{"text":"not","number":"3364"},{"text":"reward","number":"3408"},{"text":"my","number":"3450"},{"text":"name","number":"3686"},{"text":"whosoever","number":"3739"},{"text":"because","number":"3754"},{"text":"a cup","number":"4221"},{"text":"shall give","number":"4222"},{"text":"to drink","number":"4222"},{"text":"of water","number":"5204"},{"text":"you","number":"5209"},{"text":"unto you","number":"5213"},{"text":"to Christ","number":"5547"}],"2":[{"text":"leadeth","number":"399"},{"text":"up","number":"399"},{"text":"them","number":"846"},{"text":"them","number":"846"},{"text":"into","number":"1519"},{"text":"before","number":"1715"},{"text":"six","number":"1803"},{"text":"days","number":"2250"},{"text":"James","number":"2385"},{"text":"Jesus","number":"2424"},{"text":"John","number":"2491"},{"text":"And","number":"2532"},{"text":"and","number":"2532"},{"text":"and","number":"2532"},{"text":"and","number":"2532"},{"text":"and","number":"2532"},{"text":"apart","number":"2596"},{"text":"after","number":"3326"},{"text":"he was transfigured","number":"3339"},{"text":"by themselves","number":"3441"},{"text":"mountain","number":"3735"},{"text":"taketh","number":"3880"},{"text":"with him Peter","number":"4074"},{"text":"an high","number":"5308"}],"19":[{"text":"shall I suffer","number":"430"},{"text":"faithless","number":"571"},{"text":"He answereth","number":"611"},{"text":"him","number":"846"},{"text":"him","number":"846"},{"text":"generation","number":"1074"},{"text":"and","number":"1161"},{"text":"shall I be","number":"2071"},{"text":"how long","number":"2193"},{"text":"how long","number":"2193"},{"text":"saith","number":"3004"},{"text":"me","number":"3165"},{"text":"unto","number":"4314"},{"text":"with","number":"4314"},{"text":"you","number":"5209"},{"text":"you","number":"5216"},{"text":"bring","number":"5342"},{"text":"O","number":"5599"}],"12":[{"text":"of man","number":"444"},{"text":"and restoreth","number":"600"},{"text":"he answered","number":"611"},{"text":"them","number":"846"},{"text":"it is written","number":"1125"},{"text":"And","number":"1161"},{"text":"be set at nought","number":"1847"},{"text":"of","number":"1909"},{"text":"and told","number":"2036"},{"text":"cometh","number":"2064"},{"text":"Elias","number":"2243"},{"text":"that","number":"2443"},{"text":"and","number":"2532"},{"text":"and","number":"2532"},{"text":"verily","number":"3303"},{"text":"all things","number":"3956"},{"text":"he must suffer","number":"3958"},{"text":"many things","number":"4183"},{"text":"first","number":"4412"},{"text":"how","number":"4459"},{"text":"the Son","number":"5207"}],"31":[{"text":"of man","number":"444"},{"text":"of men","number":"444"},{"text":"he shall rise","number":"450"},{"text":"after that he is killed","number":"615"},{"text":"they shall kill","number":"615"},{"text":"him","number":"846"},{"text":"unto them","number":"846"},{"text":"his","number":"848"},{"text":"For","number":"1063"},{"text":"he taught","number":"1321"},{"text":"into","number":"1519"},{"text":"day","number":"2250"},{"text":"and","number":"2532"},{"text":"and","number":"2532"},{"text":"and","number":"2532"},{"text":"said","number":"3004"},{"text":"disciples","number":"3101"},{"text":"is delivered","number":"3860"},{"text":"the third","number":"5154"},{"text":"The Son","number":"5207"},{"text":"the hands","number":"5495"}],"9":[{"text":"of man","number":"444"},{"text":"were risen","number":"450"},{"text":"from","number":"575"},{"text":"them","number":"846"},{"text":"And","number":"1161"},{"text":"he charged","number":"1291"},{"text":"they should tell","number":"1334"},{"text":"they had seen","number":"1492"},{"text":"till","number":"1508"},{"text":"from","number":"1537"},{"text":"that","number":"2443"},{"text":"as they came down","number":"2597"},{"text":"no man","number":"3367"},{"text":"the dead","number":"3498"},{"text":"the mountain","number":"3735"},{"text":"what things","number":"3739"},{"text":"the Son","number":"5207"}],"27":[{"text":"he arose","number":"450"},{"text":"him","number":"846"},{"text":"him","number":"846"},{"text":"But","number":"1161"},{"text":"and lifted","number":"1453"},{"text":"up","number":"1453"},{"text":"Jesus","number":"2424"},{"text":"and","number":"2532"},{"text":"took","number":"2902"},{"text":"by the hand","number":"5495"}],"10":[{"text":"the rising","number":"450"},{"text":"themselves","number":"1438"},{"text":"from","number":"1537"},{"text":"should mean","number":"2076"},{"text":"And","number":"2532"},{"text":"they kept","number":"2902"},{"text":"that saying","number":"3056"},{"text":"the dead","number":"3498"},{"text":"with","number":"4314"},{"text":"questioning one with another","number":"4802"},{"text":"what","number":"5101"}],"43":[{"text":"to go","number":"565"},{"text":"cut","number":"609"},{"text":"off","number":"609"},{"text":"that never shall be quenched","number":"762"},{"text":"it","number":"846"},{"text":"hell","number":"1067"},{"text":"two","number":"1417"},{"text":"if","number":"1437"},{"text":"into","number":"1519"},{"text":"into","number":"1519"},{"text":"into","number":"1519"},{"text":"to enter","number":"1525"},{"text":"it is","number":"2076"},{"text":"having","number":"2192"},{"text":"life","number":"2222"},{"text":"than","number":"2228"},{"text":"And","number":"2532"},{"text":"better","number":"2570"},{"text":"maimed","number":"2948"},{"text":"the fire","number":"4442"},{"text":"thee","number":"4571"},{"text":"offend","number":"4624"},{"text":"for thee","number":"4671"},{"text":"thy","number":"4675"},{"text":"hand","number":"5495"},{"text":"hands","number":"5495"}],"24":[{"text":"unbelief","number":"570"},{"text":"help thou","number":"997"},{"text":"tears","number":"1144"},{"text":"straightway","number":"2112"},{"text":"And","number":"2532"},{"text":"cried out","number":"2896"},{"text":"Lord","number":"2962"},{"text":"and said","number":"3004"},{"text":"with","number":"3326"},{"text":"mine","number":"3450"},{"text":"of the child","number":"3813"},{"text":"the father","number":"3962"},{"text":"I believe","number":"4100"}],"26":[{"text":"He is dead","number":"599"},{"text":"him","number":"846"},{"text":"he was","number":"1096"},{"text":"and came out of him","number":"1831"},{"text":"And","number":"2532"},{"text":"and","number":"2532"},{"text":"and","number":"2532"},{"text":"the spirit cried","number":"2896"},{"text":"said","number":"3004"},{"text":"one dead","number":"3498"},{"text":"that","number":"3754"},{"text":"many","number":"4183"},{"text":"sore","number":"4183"},{"text":"rent","number":"4682"},{"text":"as","number":"5616"},{"text":"insomuch","number":"5620"}],"45":[{"text":"cut","number":"609"},{"text":"off","number":"609"},{"text":"that never shall be quenched","number":"762"},{"text":"it","number":"846"},{"text":"to be cast","number":"906"},{"text":"hell","number":"1067"},{"text":"two","number":"1417"},{"text":"if","number":"1437"},{"text":"into","number":"1519"},{"text":"into","number":"1519"},{"text":"into","number":"1519"},{"text":"to enter","number":"1525"},{"text":"it is","number":"2076"},{"text":"having","number":"2192"},{"text":"life","number":"2222"},{"text":"than","number":"2228"},{"text":"And","number":"2532"},{"text":"better","number":"2570"},{"text":"feet","number":"4228"},{"text":"foot","number":"4228"},{"text":"the fire","number":"4442"},{"text":"thee","number":"4571"},{"text":"offend","number":"4624"},{"text":"for thee","number":"4671"},{"text":"thy","number":"4675"},{"text":"halt","number":"5560"}],"5":[{"text":"answered","number":"611"},{"text":"to be","number":"1511"},{"text":"it is","number":"2076"},{"text":"for Elias","number":"2243"},{"text":"for us","number":"2248"},{"text":"to Jesus","number":"2424"},{"text":"And","number":"2532"},{"text":"and","number":"2532"},{"text":"and","number":"2532"},{"text":"and","number":"2532"},{"text":"good","number":"2570"},{"text":"and said","number":"3004"},{"text":"one","number":"3391"},{"text":"one","number":"3391"},{"text":"one","number":"3391"},{"text":"for Moses","number":"3475"},{"text":"Peter","number":"4074"},{"text":"let us make","number":"4160"},{"text":"Master","number":"4461"},{"text":"tabernacles","number":"4633"},{"text":"for thee","number":"4671"},{"text":"three","number":"5140"},{"text":"here","number":"5602"}],"15":[{"text":"him saluted","number":"782"},{"text":"him","number":"846"},{"text":"him","number":"846"},{"text":"when they beheld","number":"1492"},{"text":"were greatly amazed","number":"1568"},{"text":"straightway","number":"2112"},{"text":"And","number":"2532"},{"text":"and","number":"2532"},{"text":"the people","number":"3793"},{"text":"all","number":"3956"},{"text":"running to","number":"4370"}],"42":[{"text":"for him","number":"846"},{"text":"his","number":"846"},{"text":"he were cast","number":"906"},{"text":"that","number":"1487"},{"text":"in","number":"1519"},{"text":"into","number":"1519"},{"text":"one","number":"1520"},{"text":"me","number":"1691"},{"text":"it is","number":"2076"},{"text":"the sea","number":"2281"},{"text":"And","number":"2532"},{"text":"and","number":"2532"},{"text":"better","number":"2570"},{"text":"a millstone","number":"3037"},{"text":"of these little ones","number":"3398"},{"text":"whosoever","number":"3739"},{"text":"about","number":"4012"},{"text":"were hanged","number":"4029"},{"text":"that believe","number":"4100"},{"text":"shall offend","number":"4624"},{"text":"neck","number":"5137"}],"11":[{"text":"him","number":"846"},{"text":"the scribes","number":"1122"},{"text":"must","number":"1163"},{"text":"they asked","number":"1905"},{"text":"come","number":"2064"},{"text":"Elias","number":"2243"},{"text":"And","number":"2532"},{"text":"say","number":"3004"},{"text":"saying","number":"3004"},{"text":"Why","number":"3754"},{"text":"that","number":"3754"},{"text":"first","number":"4412"}],"18":[{"text":"him","number":"846"},{"text":"him","number":"846"},{"text":"him","number":"846"},{"text":"with his","number":"848"},{"text":"he foameth","number":"875"},{"text":"out","number":"1544"},{"text":"they should cast","number":"1544"},{"text":"I spake","number":"2036"},{"text":"that","number":"2443"},{"text":"they could","number":"2480"},{"text":"And","number":"2532"},{"text":"and","number":"2532"},{"text":"and","number":"2532"},{"text":"and","number":"2532"},{"text":"and","number":"2532"},{"text":"and","number":"2532"},{"text":"he taketh","number":"2638"},{"text":"disciples","number":"3101"},{"text":"pineth away","number":"3583"},{"text":"teeth","number":"3599"},{"text":"wheresoever","number":"3699"},{"text":"not","number":"3756"},{"text":"he teareth","number":"4486"},{"text":"to thy","number":"4675"},{"text":"gnasheth","number":"5149"}],"20":[{"text":"him","number":"846"},{"text":"him","number":"846"},{"text":"him","number":"846"},{"text":"him","number":"846"},{"text":"foaming","number":"875"},{"text":"the ground","number":"1093"},{"text":"when he saw","number":"1492"},{"text":"on","number":"1909"},{"text":"straightway","number":"2112"},{"text":"And","number":"2532"},{"text":"and","number":"2532"},{"text":"and","number":"2532"},{"text":"and wallowed","number":"2947"},{"text":"he fell","number":"4098"},{"text":"the spirit","number":"4151"},{"text":"unto","number":"4314"},{"text":"tare","number":"4682"},{"text":"they brought","number":"5342"}],"28":[{"text":"him","number":"846"},{"text":"him","number":"846"},{"text":"his","number":"846"},{"text":"could","number":"1410"},{"text":"into","number":"1519"},{"text":"when he was come","number":"1525"},{"text":"cast","number":"1544"},{"text":"out","number":"1544"},{"text":"asked","number":"1905"},{"text":"we","number":"2249"},{"text":"And","number":"2532"},{"text":"privately","number":"2596"},{"text":"disciples","number":"3101"},{"text":"the house","number":"3624"},{"text":"Why","number":"3754"},{"text":"not","number":"3756"}],"36":[{"text":"him","number":"846"},{"text":"him","number":"846"},{"text":"of them","number":"846"},{"text":"unto them","number":"846"},{"text":"in","number":"1722"},{"text":"in his arms","number":"1723"},{"text":"when he had taken","number":"1723"},{"text":"he said","number":"2036"},{"text":"and set","number":"2476"},{"text":"And","number":"2532"},{"text":"and","number":"2532"},{"text":"he took","number":"2983"},{"text":"the midst","number":"3319"},{"text":"a child","number":"3813"}],"39":[{"text":"him","number":"846"},{"text":"for","number":"1063"},{"text":"But","number":"1161"},{"text":"can","number":"1410"},{"text":"a miracle","number":"1411"},{"text":"in","number":"1909"},{"text":"said","number":"2036"},{"text":"there is","number":"2076"},{"text":"Jesus","number":"2424"},{"text":"that","number":"2532"},{"text":"speak evil","number":"2551"},{"text":"Forbid","number":"2967"},{"text":"of me","number":"3165"},{"text":"not","number":"3361"},{"text":"my","number":"3450"},{"text":"name","number":"3686"},{"text":"which","number":"3739"},{"text":"no man","number":"3762"},{"text":"shall do","number":"4160"},{"text":"lightly","number":"5035"}],"3":[{"text":"his","number":"846"},{"text":"them","number":"846"},{"text":"earth","number":"1093"},{"text":"became","number":"1096"},{"text":"fuller","number":"1102"},{"text":"can","number":"1410"},{"text":"on","number":"1909"},{"text":"raiment","number":"2440"},{"text":"And","number":"2532"},{"text":"white","number":"3021"},{"text":"white","number":"3022"},{"text":"exceeding","number":"3029"},{"text":"so as","number":"3634"},{"text":"no","number":"3756"},{"text":"shining","number":"4744"},{"text":"snow","number":"5510"},{"text":"as","number":"5613"}],"47":[{"text":"it","number":"846"},{"text":"to be cast","number":"906"},{"text":"the kingdom","number":"932"},{"text":"hell","number":"1067"},{"text":"two","number":"1417"},{"text":"if","number":"1437"},{"text":"into","number":"1519"},{"text":"into","number":"1519"},{"text":"to enter","number":"1525"},{"text":"out","number":"1544"},{"text":"pluck","number":"1544"},{"text":"it is","number":"2076"},{"text":"having","number":"2192"},{"text":"than","number":"2228"},{"text":"of God","number":"2316"},{"text":"And","number":"2532"},{"text":"better","number":"2570"},{"text":"with one eye","number":"3442"},{"text":"eye","number":"3788"},{"text":"eyes","number":"3788"},{"text":"fire","number":"4442"},{"text":"thee","number":"4571"},{"text":"offend","number":"4624"},{"text":"for thee","number":"4671"},{"text":"thine","number":"4675"}],"44":[{"text":"their","number":"846"},{"text":"and","number":"2532"},{"text":"Where","number":"3699"},{"text":"not","number":"3756"},{"text":"not","number":"3756"},{"text":"the fire","number":"4442"},{"text":"is","number":"4570"},{"text":"quenched","number":"4570"},{"text":"worm","number":"4663"},{"text":"dieth","number":"5053"}],"46":[{"text":"their","number":"846"},{"text":"and","number":"2532"},{"text":"Where","number":"3699"},{"text":"not","number":"3756"},{"text":"not","number":"3756"},{"text":"the fire","number":"4442"},{"text":"is","number":"4570"},{"text":"quenched","number":"4570"},{"text":"worm","number":"4663"},{"text":"dieth","number":"5053"}],"48":[{"text":"their","number":"846"},{"text":"and","number":"2532"},{"text":"Where","number":"3699"},{"text":"not","number":"3756"},{"text":"not","number":"3756"},{"text":"the fire","number":"4442"},{"text":"is","number":"4570"},{"text":"quenched","number":"4570"},{"text":"worm","number":"4663"},{"text":"dieth","number":"5053"}],"14":[{"text":"them","number":"846"},{"text":"with them","number":"846"},{"text":"the scribes","number":"1122"},{"text":"he saw","number":"1492"},{"text":"when he came","number":"2064"},{"text":"And","number":"2532"},{"text":"and","number":"2532"},{"text":"his disciples","number":"3101"},{"text":"multitude","number":"3793"},{"text":"about","number":"4012"},{"text":"a great","number":"4183"},{"text":"to","number":"4314"},{"text":"questioning","number":"4802"}],"33":[{"text":"them","number":"846"},{"text":"being","number":"1096"},{"text":"was it that ye disputed","number":"1260"},{"text":"yourselves","number":"1438"},{"text":"to","number":"1519"},{"text":"by","number":"1722"},{"text":"in","number":"1722"},{"text":"he asked","number":"1905"},{"text":"he came","number":"2064"},{"text":"And","number":"2532"},{"text":"and","number":"2532"},{"text":"Capernaum","number":"2584"},{"text":"the way","number":"3598"},{"text":"the house","number":"3614"},{"text":"among","number":"4314"},{"text":"What","number":"5101"}],"23":[{"text":"to him","number":"846"},{"text":"unto him","number":"846"},{"text":"thou canst","number":"1410"},{"text":"are possible","number":"1415"},{"text":"If","number":"1487"},{"text":"said","number":"2036"},{"text":"Jesus","number":"2424"},{"text":"all things","number":"3956"},{"text":"believe","number":"4100"},{"text":"that believeth","number":"4100"}],"21":[{"text":"unto him","number":"846"},{"text":"came","number":"1096"},{"text":"And","number":"1161"},{"text":"he asked","number":"1905"},{"text":"he said","number":"2036"},{"text":"is it","number":"2076"},{"text":"And","number":"2532"},{"text":"Of a child","number":"3812"},{"text":"his father","number":"3962"},{"text":"How long","number":"4214"},{"text":"this","number":"5124"},{"text":"ago","number":"5550"},{"text":"since","number":"5613"}],"29":[{"text":"unto them","number":"846"},{"text":"kind","number":"1085"},{"text":"can","number":"1410"},{"text":"but","number":"1508"},{"text":"by","number":"1722"},{"text":"by","number":"1722"},{"text":"come forth","number":"1831"},{"text":"he said","number":"2036"},{"text":"And","number":"2532"},{"text":"and","number":"2532"},{"text":"fasting","number":"3521"},{"text":"nothing","number":"3762"},{"text":"prayer","number":"4335"},{"text":"This","number":"5124"}],"35":[{"text":"unto them","number":"846"},{"text":"servant","number":"1249"},{"text":"the twelve","number":"1427"},{"text":"to be","number":"1511"},{"text":"If any man","number":"1536"},{"text":"the same shall be","number":"2071"},{"text":"last","number":"2078"},{"text":"desire","number":"2309"},{"text":"he sat down","number":"2523"},{"text":"And","number":"2532"},{"text":"and","number":"2532"},{"text":"and","number":"2532"},{"text":"saith","number":"3004"},{"text":"of all","number":"3956"},{"text":"of all","number":"3956"},{"text":"first","number":"4413"},{"text":"and called","number":"5455"}],"4":[{"text":"unto them","number":"846"},{"text":"Elias","number":"2243"},{"text":"they were","number":"2258"},{"text":"with Jesus","number":"2424"},{"text":"And","number":"2532"},{"text":"and","number":"2532"},{"text":"Moses","number":"3475"},{"text":"there appeared","number":"3700"},{"text":"talking","number":"4814"},{"text":"with","number":"4862"}],"16":[{"text":"them","number":"848"},{"text":"the scribes","number":"1122"},{"text":"he asked","number":"1905"},{"text":"And","number":"2532"},{"text":"with","number":"4314"},{"text":"question ye","number":"4802"},{"text":"What","number":"5101"}],"30":[{"text":"Galilee","number":"1056"},{"text":"should know","number":"1097"},{"text":"through","number":"1223"},{"text":"thence","number":"1564"},{"text":"they departed","number":"1831"},{"text":"he would","number":"2309"},{"text":"that","number":"2443"},{"text":"And","number":"2532"},{"text":"and","number":"2532"},{"text":"not","number":"3756"},{"text":"and passed","number":"3899"},{"text":"any man","number":"5100"}],"40":[{"text":"For","number":"1063"},{"text":"he that is","number":"2076"},{"text":"is","number":"2076"},{"text":"our","number":"2257"},{"text":"us","number":"2257"},{"text":"against","number":"2596"},{"text":"not","number":"3756"},{"text":"on","number":"5228"},{"text":"part","number":"5228"}],"6":[{"text":"For","number":"1063"},{"text":"for","number":"1063"},{"text":"he wist","number":"1492"},{"text":"afraid","number":"1630"},{"text":"they were sore","number":"2258"},{"text":"to say","number":"2980"},{"text":"not","number":"3756"},{"text":"what","number":"5101"}]}