{"46":[{"text":"good thing","number":"18"},{"text":"unto him","number":"846"},{"text":"unto him","number":"846"},{"text":"Can","number":"1410"},{"text":"see","number":"1492"},{"text":"come","number":"1511"},{"text":"out of","number":"1537"},{"text":"said","number":"2036"},{"text":"Come","number":"2064"},{"text":"And","number":"2532"},{"text":"and","number":"2532"},{"text":"saith","number":"3004"},{"text":"Nazareth","number":"3478"},{"text":"Nathanael","number":"3482"},{"text":"there any","number":"5100"},{"text":"Philip","number":"5376"}],"51":[{"text":"the angels","number":"32"},{"text":"Verily","number":"281"},{"text":"verily","number":"281"},{"text":"ascending","number":"305"},{"text":"of man","number":"444"},{"text":"open","number":"455"},{"text":"Hereafter","number":"575"},{"text":"unto him","number":"846"},{"text":"upon","number":"1909"},{"text":"of God","number":"2316"},{"text":"And","number":"2532"},{"text":"and","number":"2532"},{"text":"and","number":"2532"},{"text":"descending","number":"2597"},{"text":"I say","number":"3004"},{"text":"he saith","number":"3004"},{"text":"ye shall see","number":"3700"},{"text":"heaven","number":"3772"},{"text":"the Son","number":"5207"},{"text":"unto you","number":"5213"}],"33":[{"text":"the Holy","number":"40"},{"text":"but","number":"235"},{"text":"him","number":"846"},{"text":"him","number":"846"},{"text":"he which baptizeth","number":"907"},{"text":"to baptize","number":"907"},{"text":"knew","number":"1492"},{"text":"thou shalt see","number":"1492"},{"text":"the same","number":"1565"},{"text":"with","number":"1722"},{"text":"with","number":"1722"},{"text":"Upon","number":"1909"},{"text":"on","number":"1909"},{"text":"said","number":"2036"},{"text":"is","number":"2076"},{"text":"And I","number":"2504"},{"text":"and","number":"2532"},{"text":"descending","number":"2597"},{"text":"me","number":"3165"},{"text":"remaining","number":"3306"},{"text":"unto me","number":"3427"},{"text":"whom","number":"3739"},{"text":"not","number":"3756"},{"text":"the same","number":"3778"},{"text":"he that sent","number":"3992"},{"text":"Ghost","number":"4151"},{"text":"the Spirit","number":"4151"},{"text":"water","number":"5204"}],"42":[{"text":"he brought","number":"71"},{"text":"him","number":"846"},{"text":"him","number":"846"},{"text":"And","number":"1161"},{"text":"art","number":"1488"},{"text":"beheld","number":"1689"},{"text":"he said","number":"2036"},{"text":"is by interpretation","number":"2059"},{"text":"Jesus","number":"2424"},{"text":"when Jesus","number":"2424"},{"text":"of Jona","number":"2495"},{"text":"And","number":"2532"},{"text":"shalt be called","number":"2564"},{"text":"Cephas","number":"2786"},{"text":"which","number":"3739"},{"text":"A stone","number":"4074"},{"text":"to","number":"4314"},{"text":"Simon","number":"4613"},{"text":"Thou","number":"4771"},{"text":"thou","number":"4771"},{"text":"the son","number":"5207"}],"40":[{"text":"brother","number":"80"},{"text":"followed","number":"190"},{"text":"heard","number":"191"},{"text":"Andrew","number":"406"},{"text":"him","number":"846"},{"text":"the two","number":"1417"},{"text":"One","number":"1520"},{"text":"of","number":"1537"},{"text":"was","number":"2258"},{"text":"John","number":"2491"},{"text":"speak and","number":"2532"},{"text":"which","number":"3588"},{"text":"Peter's","number":"4074"},{"text":"Simon","number":"4613"}],"41":[{"text":"brother","number":"80"},{"text":"unto him","number":"846"},{"text":"is","number":"2076"},{"text":"We have found","number":"2147"},{"text":"findeth","number":"2147"},{"text":"his own","number":"2398"},{"text":"and","number":"2532"},{"text":"saith","number":"3004"},{"text":"being interpreted","number":"3177"},{"text":"the Messias","number":"3323"},{"text":"which","number":"3739"},{"text":"He","number":"3778"},{"text":"first","number":"4413"},{"text":"Simon","number":"4613"},{"text":"the Christ","number":"5547"}],"13":[{"text":"blood","number":"129"},{"text":"but","number":"235"},{"text":"of man","number":"435"},{"text":"were born","number":"1080"},{"text":"of","number":"1537"},{"text":"of","number":"1537"},{"text":"of","number":"1537"},{"text":"of","number":"1537"},{"text":"the will","number":"2307"},{"text":"the will","number":"2307"},{"text":"God","number":"2316"},{"text":"Which","number":"3739"},{"text":"not","number":"3756"},{"text":"nor","number":"3761"},{"text":"nor","number":"3761"},{"text":"of the flesh","number":"4561"}],"29":[{"text":"taketh away","number":"142"},{"text":"the sin","number":"266"},{"text":"the Lamb","number":"286"},{"text":"him","number":"846"},{"text":"seeth","number":"991"},{"text":"The next day","number":"1887"},{"text":"coming","number":"2064"},{"text":"of God","number":"2316"},{"text":"Behold","number":"2396"},{"text":"Jesus","number":"2424"},{"text":"John","number":"2491"},{"text":"and","number":"2532"},{"text":"of the world","number":"2889"},{"text":"saith","number":"3004"},{"text":"which","number":"3588"},{"text":"unto","number":"4314"}],"43":[{"text":"Follow","number":"190"},{"text":"unto him","number":"846"},{"text":"Galilee","number":"1056"},{"text":"into","number":"1519"},{"text":"go forth","number":"1831"},{"text":"The day following","number":"1887"},{"text":"findeth","number":"2147"},{"text":"would","number":"2309"},{"text":"Jesus","number":"2424"},{"text":"and","number":"2532"},{"text":"and","number":"2532"},{"text":"saith","number":"3004"},{"text":"me","number":"3427"},{"text":"Philip","number":"5376"}],"38":[{"text":"following","number":"190"},{"text":"them","number":"846"},{"text":"unto him","number":"846"},{"text":"unto them","number":"846"},{"text":"Then","number":"1161"},{"text":"Master","number":"1320"},{"text":"They said","number":"2036"},{"text":"being interpreted","number":"2059"},{"text":"seek ye","number":"2212"},{"text":"saw","number":"2300"},{"text":"Jesus","number":"2424"},{"text":"and","number":"2532"},{"text":"(which is to say","number":"3004"},{"text":"and saith","number":"3004"},{"text":"dwellest thou","number":"3306"},{"text":"where","number":"4226"},{"text":"Rabbi","number":"4461"},{"text":"turned","number":"4762"},{"text":"What","number":"5101"}],"37":[{"text":"they followed","number":"190"},{"text":"heard","number":"191"},{"text":"him","number":"846"},{"text":"the two","number":"1417"},{"text":"Jesus","number":"2424"},{"text":"And","number":"2532"},{"text":"and","number":"2532"},{"text":"speak","number":"2980"},{"text":"disciples","number":"3101"}],"14":[{"text":"truth","number":"225"},{"text":"his","number":"846"},{"text":"was made","number":"1096"},{"text":"glory","number":"1391"},{"text":"the glory","number":"1391"},{"text":"among","number":"1722"},{"text":"us","number":"2254"},{"text":"we beheld","number":"2300"},{"text":"(and","number":"2532"},{"text":"And","number":"2532"},{"text":"and","number":"2532"},{"text":"and","number":"2532"},{"text":"the Word","number":"3056"},{"text":"of the only begotten","number":"3439"},{"text":"of","number":"3844"},{"text":"the Father","number":"3962"},{"text":"full","number":"4134"},{"text":"flesh","number":"4561"},{"text":"dwelt","number":"4637"},{"text":"of grace","number":"5485"},{"text":"as","number":"5613"}],"17":[{"text":"truth","number":"225"},{"text":"came","number":"1096"},{"text":"by","number":"1223"},{"text":"by","number":"1223"},{"text":"was given","number":"1325"},{"text":"Jesus","number":"2424"},{"text":"and","number":"2532"},{"text":"Moses","number":"3475"},{"text":"the law","number":"3551"},{"text":"For","number":"3754"},{"text":"but grace","number":"5485"},{"text":"Christ","number":"5547"}],"9":[{"text":"the true","number":"228"},{"text":"into","number":"1519"},{"text":"that cometh","number":"2064"},{"text":"That was","number":"2258"},{"text":"the world","number":"2889"},{"text":"which","number":"3739"},{"text":"every man","number":"3956"},{"text":"Light","number":"5457"},{"text":"lighteth","number":"5461"}],"47":[{"text":"indeed","number":"230"},{"text":"him","number":"846"},{"text":"him","number":"848"},{"text":"guile","number":"1388"},{"text":"saw","number":"1492"},{"text":"in","number":"1722"},{"text":"coming","number":"2064"},{"text":"is","number":"2076"},{"text":"Behold","number":"2396"},{"text":"Jesus","number":"2424"},{"text":"an Israelite","number":"2475"},{"text":"and","number":"2532"},{"text":"saith","number":"3004"},{"text":"Nathanael","number":"3482"},{"text":"whom","number":"3739"},{"text":"no","number":"3756"},{"text":"of","number":"4012"},{"text":"to","number":"4314"}],"31":[{"text":"but","number":"235"},{"text":"him","number":"846"},{"text":"baptizing","number":"907"},{"text":"therefore","number":"1223"},{"text":"I","number":"1473"},{"text":"knew","number":"1492"},{"text":"with","number":"1722"},{"text":"am","number":"2064"},{"text":"come","number":"2064"},{"text":"that","number":"2443"},{"text":"to Israel","number":"2474"},{"text":"And I","number":"2504"},{"text":"not","number":"3756"},{"text":"water","number":"5204"},{"text":"he should be made manifest","number":"5319"}],"8":[{"text":"but","number":"235"},{"text":"that","number":"1565"},{"text":"He was","number":"2258"},{"text":"was sent to","number":"2443"},{"text":"bear witness","number":"3140"},{"text":"not","number":"3756"},{"text":"of","number":"4012"},{"text":"Light","number":"5457"},{"text":"that Light","number":"5457"}],"36":[{"text":"the Lamb","number":"286"},{"text":"looking upon","number":"1689"},{"text":"of God","number":"2316"},{"text":"Behold","number":"2396"},{"text":"Jesus","number":"2424"},{"text":"And","number":"2532"},{"text":"he saith","number":"3004"},{"text":"as he walked","number":"4043"}],"44":[{"text":"Andrew","number":"406"},{"text":"of","number":"575"},{"text":"Bethsaida","number":"966"},{"text":"Now","number":"1161"},{"text":"of","number":"1537"},{"text":"was","number":"2258"},{"text":"and","number":"2532"},{"text":"Peter","number":"4074"},{"text":"the city","number":"4172"},{"text":"Philip","number":"5376"}],"30":[{"text":"a man","number":"435"},{"text":"is preferred","number":"1096"},{"text":"I","number":"1473"},{"text":"before","number":"1715"},{"text":"said","number":"2036"},{"text":"cometh","number":"2064"},{"text":"is he","number":"2076"},{"text":"he was","number":"2258"},{"text":"me","number":"3450"},{"text":"me","number":"3450"},{"text":"me","number":"3450"},{"text":"After","number":"3694"},{"text":"which","number":"3739"},{"text":"whom","number":"3739"},{"text":"for","number":"3754"},{"text":"This","number":"3778"},{"text":"of","number":"4012"},{"text":"before","number":"4413"}],"6":[{"text":"a man","number":"444"},{"text":"sent","number":"649"},{"text":"whose","number":"846"},{"text":"There was","number":"1096"},{"text":"God","number":"2316"},{"text":"was John","number":"2491"},{"text":"name","number":"3686"},{"text":"from","number":"3844"}],"4":[{"text":"of men","number":"444"},{"text":"him","number":"846"},{"text":"In","number":"1722"},{"text":"life","number":"2222"},{"text":"the life","number":"2222"},{"text":"was","number":"2258"},{"text":"was","number":"2258"},{"text":"and","number":"2532"},{"text":"the light","number":"5457"}],"16":[{"text":"for","number":"473"},{"text":"his","number":"846"},{"text":"of","number":"1537"},{"text":"we","number":"2249"},{"text":"And","number":"2532"},{"text":"and","number":"2532"},{"text":"have","number":"2983"},{"text":"received","number":"2983"},{"text":"all","number":"3956"},{"text":"fulness","number":"4138"},{"text":"grace","number":"5485"},{"text":"grace","number":"5485"}],"27":[{"text":"worthy","number":"514"},{"text":"He","number":"846"},{"text":"is preferred","number":"1096"},{"text":"I","number":"1473"},{"text":"am","number":"1510"},{"text":"before","number":"1715"},{"text":"coming","number":"2064"},{"text":"it is","number":"2076"},{"text":"latchet","number":"2438"},{"text":"to","number":"2443"},{"text":"unloose","number":"3089"},{"text":"me","number":"3450"},{"text":"me","number":"3450"},{"text":"after","number":"3694"},{"text":"who","number":"3739"},{"text":"whose","number":"3739"},{"text":"not","number":"3756"},{"text":"shoe's","number":"5266"}],"45":[{"text":"of","number":"575"},{"text":"unto him","number":"846"},{"text":"did write","number":"1125"},{"text":"in","number":"1722"},{"text":"We have found","number":"2147"},{"text":"findeth","number":"2147"},{"text":"Jesus","number":"2424"},{"text":"of Joseph","number":"2501"},{"text":"and","number":"2532"},{"text":"and","number":"2532"},{"text":"saith","number":"3004"},{"text":"Moses","number":"3475"},{"text":"Nazareth","number":"3478"},{"text":"Nathanael","number":"3482"},{"text":"the law","number":"3551"},{"text":"him of whom","number":"3739"},{"text":"the prophets","number":"4396"},{"text":"the son","number":"5207"},{"text":"Philip","number":"5376"}],"26":[{"text":"answered","number":"611"},{"text":"them","number":"846"},{"text":"baptize","number":"907"},{"text":"but","number":"1161"},{"text":"I","number":"1473"},{"text":"know","number":"1492"},{"text":"with","number":"1722"},{"text":"there standeth one","number":"2476"},{"text":"John","number":"2491"},{"text":"saying","number":"3004"},{"text":"among","number":"3319"},{"text":"whom","number":"3739"},{"text":"not","number":"3756"},{"text":"water","number":"5204"},{"text":"ye","number":"5210"},{"text":"you","number":"5216"}],"48":[{"text":"answered","number":"611"},{"text":"unto him","number":"846"},{"text":"unto him","number":"846"},{"text":"knowest thou","number":"1097"},{"text":"I saw","number":"1492"},{"text":"said","number":"2036"},{"text":"Jesus","number":"2424"},{"text":"and","number":"2532"},{"text":"saith","number":"3004"},{"text":"me","number":"3165"},{"text":"Nathanael","number":"3482"},{"text":"Whence","number":"4159"},{"text":"Before","number":"4253"},{"text":"thee","number":"4571"},{"text":"thee","number":"4571"},{"text":"the fig tree","number":"4808"},{"text":"under","number":"5259"},{"text":"that Philip","number":"5376"},{"text":"called","number":"5455"},{"text":"when thou wast","number":"5607"}],"49":[{"text":"answered","number":"611"},{"text":"unto him","number":"846"},{"text":"the King","number":"935"},{"text":"art","number":"1488"},{"text":"art","number":"1488"},{"text":"of God","number":"2316"},{"text":"of Israel","number":"2474"},{"text":"and","number":"2532"},{"text":"saith","number":"3004"},{"text":"Nathanael","number":"3482"},{"text":"Rabbi","number":"4461"},{"text":"thou","number":"4771"},{"text":"thou","number":"4771"},{"text":"the Son","number":"5207"}],"50":[{"text":"answered","number":"611"},{"text":"unto him","number":"846"},{"text":"I saw","number":"1492"},{"text":"I said","number":"2036"},{"text":"said","number":"2036"},{"text":"Jesus","number":"2424"},{"text":"and","number":"2532"},{"text":"greater things","number":"3187"},{"text":"thou shalt see","number":"3700"},{"text":"Because","number":"3754"},{"text":"believest thou","number":"4100"},{"text":"thee","number":"4571"},{"text":"unto thee","number":"4671"},{"text":"the fig tree","number":"4808"},{"text":"than these","number":"5130"},{"text":"under","number":"5270"}],"21":[{"text":"he answered","number":"611"},{"text":"him","number":"846"},{"text":"Art","number":"1488"},{"text":"Art","number":"1488"},{"text":"I am","number":"1510"},{"text":"they asked","number":"2065"},{"text":"Elias","number":"2243"},{"text":"And","number":"2532"},{"text":"And","number":"2532"},{"text":"And","number":"2532"},{"text":"he saith","number":"3004"},{"text":"No","number":"3756"},{"text":"not","number":"3756"},{"text":"then","number":"3767"},{"text":"that prophet","number":"4396"},{"text":"thou","number":"4771"},{"text":"thou","number":"4771"},{"text":"What","number":"5101"}],"22":[{"text":"an answer","number":"612"},{"text":"unto him","number":"846"},{"text":"we may give","number":"1325"},{"text":"art thou","number":"1488"},{"text":"said they","number":"2036"},{"text":"us","number":"2248"},{"text":"that","number":"2443"},{"text":"sayest thou","number":"3004"},{"text":"Then","number":"3767"},{"text":"to them that sent","number":"3992"},{"text":"of","number":"4012"},{"text":"thyself","number":"4572"},{"text":"What","number":"5101"},{"text":"Who","number":"5101"}],"19":[{"text":"sent","number":"649"},{"text":"him","number":"846"},{"text":"art","number":"1488"},{"text":"from","number":"1537"},{"text":"ask","number":"2065"},{"text":"is","number":"2076"},{"text":"priests","number":"2409"},{"text":"Jerusalem","number":"2414"},{"text":"to","number":"2443"},{"text":"the Jews","number":"2453"},{"text":"of John","number":"2491"},{"text":"And","number":"2532"},{"text":"and","number":"2532"},{"text":"Levites","number":"3019"},{"text":"the record","number":"3141"},{"text":"when","number":"3753"},{"text":"this","number":"3778"},{"text":"thou","number":"4771"},{"text":"Who","number":"5101"}],"24":[{"text":"were sent","number":"649"},{"text":"of","number":"1537"},{"text":"were","number":"2258"},{"text":"And","number":"2532"},{"text":"they which","number":"3588"},{"text":"the Pharisees","number":"5330"}],"20":[{"text":"denied","number":"720"},{"text":"I","number":"1473"},{"text":"am","number":"1510"},{"text":"And","number":"2532"},{"text":"and","number":"2532"},{"text":"but","number":"2532"},{"text":"confessed","number":"3670"},{"text":"he confessed","number":"3670"},{"text":"not","number":"3756"},{"text":"not","number":"3756"},{"text":"the Christ","number":"5547"}],"1":[{"text":"the beginning","number":"746"},{"text":"In","number":"1722"},{"text":"was","number":"2258"},{"text":"was","number":"2258"},{"text":"was","number":"2258"},{"text":"God","number":"2316"},{"text":"God","number":"2316"},{"text":"and","number":"2532"},{"text":"and","number":"2532"},{"text":"the Word","number":"3056"},{"text":"the Word","number":"3056"},{"text":"the Word","number":"3056"},{"text":"with","number":"4314"}],"2":[{"text":"the beginning","number":"746"},{"text":"in","number":"1722"},{"text":"was","number":"2258"},{"text":"God","number":"2316"},{"text":"The same","number":"3778"},{"text":"with","number":"4314"}],"10":[{"text":"him","number":"846"},{"text":"him","number":"846"},{"text":"was made","number":"1096"},{"text":"knew","number":"1097"},{"text":"by","number":"1223"},{"text":"in","number":"1722"},{"text":"He was","number":"2258"},{"text":"and","number":"2532"},{"text":"and","number":"2532"},{"text":"the world","number":"2889"},{"text":"the world","number":"2889"},{"text":"the world","number":"2889"},{"text":"not","number":"3756"}],"11":[{"text":"him","number":"846"},{"text":"unto","number":"1519"},{"text":"He came","number":"2064"},{"text":"his own","number":"2398"},{"text":"his own","number":"2398"},{"text":"and","number":"2532"},{"text":"not","number":"3756"},{"text":"received","number":"3880"}],"12":[{"text":"him","number":"846"},{"text":"his","number":"846"},{"text":"to them","number":"846"},{"text":"to become","number":"1096"},{"text":"But","number":"1161"},{"text":"gave he","number":"1325"},{"text":"on","number":"1519"},{"text":"power","number":"1849"},{"text":"of God","number":"2316"},{"text":"received","number":"2983"},{"text":"name","number":"3686"},{"text":"as many as","number":"3745"},{"text":"even to them that believe","number":"4100"},{"text":"the sons","number":"5043"}],"15":[{"text":"him","number":"846"},{"text":"is preferred","number":"1096"},{"text":"before","number":"1715"},{"text":"I spake","number":"2036"},{"text":"He that cometh","number":"2064"},{"text":"he was","number":"2258"},{"text":"was he","number":"2258"},{"text":"John","number":"2491"},{"text":"and","number":"2532"},{"text":"cried","number":"2896"},{"text":"saying","number":"3004"},{"text":"bare witness","number":"3140"},{"text":"me","number":"3450"},{"text":"me","number":"3450"},{"text":"me","number":"3450"},{"text":"after","number":"3694"},{"text":"of whom","number":"3739"},{"text":"for","number":"3754"},{"text":"This","number":"3778"},{"text":"of","number":"4012"},{"text":"before","number":"4413"}],"25":[{"text":"him","number":"846"},{"text":"unto him","number":"846"},{"text":"baptizest thou","number":"907"},{"text":"if","number":"1487"},{"text":"be","number":"1488"},{"text":"said","number":"2036"},{"text":"they asked","number":"2065"},{"text":"Elias","number":"2243"},{"text":"And","number":"2532"},{"text":"and","number":"2532"},{"text":"not","number":"3756"},{"text":"then","number":"3767"},{"text":"neither","number":"3777"},{"text":"nor","number":"3777"},{"text":"that prophet","number":"4396"},{"text":"thou","number":"4771"},{"text":"Why","number":"5101"},{"text":"that Christ","number":"5547"}],"3":[{"text":"him","number":"846"},{"text":"him","number":"846"},{"text":"made","number":"1096"},{"text":"that was made","number":"1096"},{"text":"was","number":"1096"},{"text":"were made","number":"1096"},{"text":"by","number":"1223"},{"text":"any thing","number":"1520"},{"text":"and","number":"2532"},{"text":"not","number":"3761"},{"text":"All things","number":"3956"},{"text":"without","number":"5565"}],"32":[{"text":"him","number":"846"},{"text":"from","number":"1537"},{"text":"upon","number":"1909"},{"text":"I saw","number":"2300"},{"text":"John","number":"2491"},{"text":"And","number":"2532"},{"text":"and","number":"2532"},{"text":"descending","number":"2597"},{"text":"saying","number":"3004"},{"text":"bare record","number":"3140"},{"text":"it abode","number":"3306"},{"text":"heaven","number":"3772"},{"text":"a dove","number":"4058"},{"text":"the Spirit","number":"4151"},{"text":"like","number":"5616"}],"39":[{"text":"him","number":"846"},{"text":"unto them","number":"846"},{"text":"for","number":"1161"},{"text":"the tenth","number":"1182"},{"text":"saw","number":"1492"},{"text":"see","number":"1492"},{"text":"that","number":"1565"},{"text":"Come","number":"2064"},{"text":"They came","number":"2064"},{"text":"day","number":"2250"},{"text":"it was","number":"2258"},{"text":"and","number":"2532"},{"text":"and","number":"2532"},{"text":"and","number":"2532"},{"text":"He saith","number":"3004"},{"text":"abode","number":"3306"},{"text":"he dwelt","number":"3306"},{"text":"with","number":"3844"},{"text":"where","number":"4226"},{"text":"hour","number":"5610"},{"text":"about","number":"5613"}],"7":[{"text":"him","number":"846"},{"text":"men through","number":"1223"},{"text":"for","number":"1519"},{"text":"came","number":"2064"},{"text":"that","number":"2443"},{"text":"to","number":"2443"},{"text":"bear witness","number":"3140"},{"text":"a witness","number":"3141"},{"text":"The same","number":"3778"},{"text":"all","number":"3956"},{"text":"of","number":"4012"},{"text":"might believe","number":"4100"},{"text":"the Light","number":"5457"}],"35":[{"text":"his","number":"846"},{"text":"two","number":"1417"},{"text":"of","number":"1537"},{"text":"the next day after","number":"1887"},{"text":"stood","number":"2476"},{"text":"John","number":"2491"},{"text":"and","number":"2532"},{"text":"disciples","number":"3101"},{"text":"Again","number":"3825"}],"5":[{"text":"it","number":"846"},{"text":"in","number":"1722"},{"text":"And","number":"2532"},{"text":"and","number":"2532"},{"text":"comprehended","number":"2638"},{"text":"not","number":"3756"},{"text":"darkness","number":"4653"},{"text":"the darkness","number":"4653"},{"text":"shineth","number":"5316"},{"text":"the light","number":"5457"}],"28":[{"text":"baptizing","number":"907"},{"text":"Bethabara","number":"962"},{"text":"were done","number":"1096"},{"text":"in","number":"1722"},{"text":"was","number":"2258"},{"text":"Jordan","number":"2446"},{"text":"John","number":"2491"},{"text":"where","number":"3699"},{"text":"beyond","number":"4008"},{"text":"These things","number":"5023"}],"23":[{"text":"of one crying","number":"994"},{"text":"I","number":"1473"},{"text":"in","number":"1722"},{"text":"said","number":"2036"},{"text":"the wilderness","number":"2048"},{"text":"Make straight","number":"2116"},{"text":"Esaias","number":"2268"},{"text":"as","number":"2531"},{"text":"of the Lord","number":"2962"},{"text":"the way","number":"3598"},{"text":"the prophet","number":"4396"},{"text":"He said","number":"5346"},{"text":"am the voice","number":"5456"}],"18":[{"text":"in","number":"1519"},{"text":"he","number":"1565"},{"text":"hath declared","number":"1834"},{"text":"God","number":"2316"},{"text":"the bosom","number":"2859"},{"text":"the only begotten","number":"3439"},{"text":"which","number":"3588"},{"text":"hath seen","number":"3708"},{"text":"No man","number":"3762"},{"text":"of the Father","number":"3962"},{"text":"at any time","number":"4455"},{"text":"Son","number":"5207"},{"text":"is","number":"5607"}],"34":[{"text":"is","number":"2076"},{"text":"of God","number":"2316"},{"text":"And I","number":"2504"},{"text":"and","number":"2532"},{"text":"bare record","number":"3140"},{"text":"saw","number":"3708"},{"text":"that","number":"3754"},{"text":"this","number":"3778"},{"text":"the Son","number":"5207"}]}