{"24":[{"text":"He that loveth","number":"25"},{"text":"ye hear","number":"191"},{"text":"but","number":"235"},{"text":"mine","number":"1699"},{"text":"is","number":"2076"},{"text":"and","number":"2532"},{"text":"sayings","number":"3056"},{"text":"the word","number":"3056"},{"text":"me","number":"3165"},{"text":"me","number":"3165"},{"text":"not","number":"3361"},{"text":"my","number":"3450"},{"text":"which","number":"3588"},{"text":"which","number":"3739"},{"text":"not","number":"3756"},{"text":"not","number":"3756"},{"text":"the Father's","number":"3962"},{"text":"sent","number":"3992"},{"text":"keepeth","number":"5083"}],"31":[{"text":"I love","number":"25"},{"text":"let us go","number":"71"},{"text":"But","number":"235"},{"text":"may know","number":"1097"},{"text":"Arise","number":"1453"},{"text":"commandment","number":"1781"},{"text":"gave","number":"1781"},{"text":"hence","number":"1782"},{"text":"that","number":"2443"},{"text":"as","number":"2531"},{"text":"and","number":"2532"},{"text":"the world","number":"2889"},{"text":"me","number":"3427"},{"text":"that","number":"3754"},{"text":"even so","number":"3779"},{"text":"the Father","number":"3962"},{"text":"the Father","number":"3962"},{"text":"I do","number":"4160"}],"21":[{"text":"he that loveth","number":"25"},{"text":"shall be loved","number":"25"},{"text":"that loveth","number":"25"},{"text":"will love","number":"25"},{"text":"him","number":"846"},{"text":"them","number":"846"},{"text":"to him","number":"846"},{"text":"and","number":"1161"},{"text":"I","number":"1473"},{"text":"he","number":"1565"},{"text":"myself","number":"1683"},{"text":"will manifest","number":"1718"},{"text":"commandments","number":"1785"},{"text":"it is","number":"2076"},{"text":"He that hath","number":"2192"},{"text":"and","number":"2532"},{"text":"and","number":"2532"},{"text":"and","number":"2532"},{"text":"me","number":"3165"},{"text":"me","number":"3165"},{"text":"my","number":"3450"},{"text":"my","number":"3450"},{"text":"Father","number":"3962"},{"text":"keepeth","number":"5083"},{"text":"of","number":"5259"}],"23":[{"text":"love","number":"25"},{"text":"will love","number":"25"},{"text":"answered","number":"611"},{"text":"him","number":"846"},{"text":"him","number":"846"},{"text":"him","number":"846"},{"text":"unto him","number":"846"},{"text":"If","number":"1437"},{"text":"said","number":"2036"},{"text":"we will come","number":"2064"},{"text":"Jesus","number":"2424"},{"text":"and","number":"2532"},{"text":"and","number":"2532"},{"text":"and","number":"2532"},{"text":"and","number":"2532"},{"text":"words","number":"3056"},{"text":"me","number":"3165"},{"text":"our abode","number":"3438"},{"text":"my","number":"3450"},{"text":"my","number":"3450"},{"text":"with","number":"3844"},{"text":"Father","number":"3962"},{"text":"make","number":"4160"},{"text":"unto","number":"4314"},{"text":"he will keep","number":"5083"},{"text":"a man","number":"5100"}],"15":[{"text":"ye love","number":"25"},{"text":"If","number":"1437"},{"text":"my","number":"1699"},{"text":"commandments","number":"1785"},{"text":"me","number":"3165"},{"text":"keep","number":"5083"}],"28":[{"text":"ye loved","number":"25"},{"text":"Ye have heard","number":"191"},{"text":"I","number":"1473"},{"text":"If","number":"1487"},{"text":"I said","number":"2036"},{"text":"said","number":"2036"},{"text":"come","number":"2064"},{"text":"is","number":"2076"},{"text":"and","number":"2532"},{"text":"me","number":"3165"},{"text":"greater than","number":"3187"},{"text":"I","number":"3450"},{"text":"my","number":"3450"},{"text":"because","number":"3754"},{"text":"for","number":"3754"},{"text":"how","number":"3754"},{"text":"Father","number":"3962"},{"text":"the Father","number":"3962"},{"text":"I go","number":"4198"},{"text":"again unto","number":"4314"},{"text":"unto","number":"4314"},{"text":"you","number":"5209"},{"text":"unto you","number":"5213"},{"text":"I go away","number":"5217"},{"text":"ye would rejoice","number":"5463"}],"26":[{"text":"which is the Holy","number":"40"},{"text":"But","number":"1161"},{"text":"shall teach","number":"1321"},{"text":"he","number":"1565"},{"text":"in","number":"1722"},{"text":"I have said","number":"2036"},{"text":"and","number":"2532"},{"text":"my","number":"3450"},{"text":"name","number":"3686"},{"text":"whatsoever","number":"3739"},{"text":"whom","number":"3739"},{"text":"the Comforter","number":"3875"},{"text":"all things","number":"3956"},{"text":"all things","number":"3956"},{"text":"the Father","number":"3962"},{"text":"will send","number":"3992"},{"text":"Ghost","number":"4151"},{"text":"you","number":"5209"},{"text":"your","number":"5209"},{"text":"unto you","number":"5213"},{"text":"bring","number":"5279"},{"text":"remembrance","number":"5279"},{"text":"to","number":"5279"}],"13":[{"text":"ye shall ask","number":"154"},{"text":"may be glorified","number":"1392"},{"text":"in","number":"1722"},{"text":"in","number":"1722"},{"text":"that","number":"2443"},{"text":"And","number":"2532"},{"text":"my","number":"3450"},{"text":"name","number":"3686"},{"text":"whatsoever","number":"3748"},{"text":"the Father","number":"3962"},{"text":"will I do","number":"4160"},{"text":"that","number":"5124"},{"text":"the Son","number":"5207"}],"14":[{"text":"ye shall ask","number":"154"},{"text":"If","number":"1437"},{"text":"I","number":"1473"},{"text":"in","number":"1722"},{"text":"my","number":"3450"},{"text":"name","number":"3686"},{"text":"will do","number":"4160"},{"text":"any thing","number":"5100"}],"16":[{"text":"ever","number":"165"},{"text":"another","number":"243"},{"text":"he shall give","number":"1325"},{"text":"I","number":"1473"},{"text":"for","number":"1519"},{"text":"will pray","number":"2065"},{"text":"that","number":"2443"},{"text":"And","number":"2532"},{"text":"and","number":"2532"},{"text":"he may abide","number":"3306"},{"text":"with","number":"3326"},{"text":"Comforter","number":"3875"},{"text":"the Father","number":"3962"},{"text":"you","number":"5213"},{"text":"you","number":"5216"}],"17":[{"text":"of truth","number":"225"},{"text":"him","number":"846"},{"text":"him","number":"846"},{"text":"him","number":"846"},{"text":"know","number":"1097"},{"text":"knoweth","number":"1097"},{"text":"but","number":"1161"},{"text":"in","number":"1722"},{"text":"shall be","number":"2071"},{"text":"it seeth","number":"2334"},{"text":"and","number":"2532"},{"text":"the world","number":"2889"},{"text":"receive","number":"2983"},{"text":"he dwelleth","number":"3306"},{"text":"whom","number":"3739"},{"text":"because","number":"3754"},{"text":"for","number":"3754"},{"text":"cannot","number":"3756"},{"text":"not","number":"3756"},{"text":"neither","number":"3761"},{"text":"with","number":"3844"},{"text":"Even the Spirit","number":"4151"},{"text":"ye","number":"5210"},{"text":"you","number":"5213"},{"text":"you","number":"5213"}],"6":[{"text":"the truth","number":"225"},{"text":"unto him","number":"846"},{"text":"by","number":"1223"},{"text":"I","number":"1473"},{"text":"but","number":"1508"},{"text":"am","number":"1510"},{"text":"me","number":"1700"},{"text":"cometh","number":"2064"},{"text":"the life","number":"2222"},{"text":"Jesus","number":"2424"},{"text":"and","number":"2532"},{"text":"saith","number":"3004"},{"text":"the way","number":"3598"},{"text":"no man","number":"3762"},{"text":"the Father","number":"3962"},{"text":"unto","number":"4314"}],"12":[{"text":"Verily","number":"281"},{"text":"verily","number":"281"},{"text":"I","number":"1473"},{"text":"that I","number":"1473"},{"text":"on","number":"1519"},{"text":"me","number":"1691"},{"text":"the works","number":"2041"},{"text":"and","number":"2532"},{"text":"also","number":"2548"},{"text":"I say","number":"3004"},{"text":"greater works than","number":"3187"},{"text":"my","number":"3450"},{"text":"because","number":"3754"},{"text":"Father","number":"3962"},{"text":"He that believeth","number":"4100"},{"text":"do","number":"4160"},{"text":"shall he do","number":"4160"},{"text":"shall he do","number":"4160"},{"text":"go","number":"4198"},{"text":"unto","number":"4314"},{"text":"these","number":"5130"},{"text":"unto you","number":"5213"}],"2":[{"text":"I would have told","number":"302"},{"text":"so","number":"1161"},{"text":"if it were not","number":"1490"},{"text":"are","number":"1526"},{"text":"In","number":"1722"},{"text":"to prepare","number":"2090"},{"text":"mansions","number":"3438"},{"text":"my","number":"3450"},{"text":"house","number":"3614"},{"text":"Father's","number":"3962"},{"text":"many","number":"4183"},{"text":"I go","number":"4198"},{"text":"a place","number":"5117"},{"text":"for you","number":"5213"},{"text":"you","number":"5213"}],"7":[{"text":"from","number":"575"},{"text":"henceforth","number":"737"},{"text":"him","number":"846"},{"text":"him","number":"846"},{"text":"ye had known","number":"1097"},{"text":"ye know","number":"1097"},{"text":"ye should have known","number":"1097"},{"text":"If","number":"1487"},{"text":"also","number":"2532"},{"text":"and","number":"2532"},{"text":"and","number":"2532"},{"text":"me","number":"3165"},{"text":"my","number":"3450"},{"text":"have seen","number":"3708"},{"text":"Father","number":"3962"}],"10":[{"text":"of","number":"575"},{"text":"he","number":"846"},{"text":"but","number":"1161"},{"text":"I","number":"1473"},{"text":"I am","number":"1473"},{"text":"myself","number":"1683"},{"text":"me","number":"1698"},{"text":"in","number":"1722"},{"text":"in","number":"1722"},{"text":"in","number":"1722"},{"text":"the works","number":"2041"},{"text":"me","number":"2076"},{"text":"and","number":"2532"},{"text":"I speak","number":"2980"},{"text":"speak","number":"2980"},{"text":"that dwelleth","number":"3306"},{"text":"that","number":"3739"},{"text":"that","number":"3754"},{"text":"not","number":"3756"},{"text":"not","number":"3756"},{"text":"the Father","number":"3962"},{"text":"the Father","number":"3962"},{"text":"the Father","number":"3962"},{"text":"Believest thou","number":"4100"},{"text":"doeth","number":"4160"},{"text":"the words","number":"4487"},{"text":"unto you","number":"5213"}],"8":[{"text":"it sufficeth","number":"714"},{"text":"unto him","number":"846"},{"text":"shew","number":"1166"},{"text":"us","number":"2254"},{"text":"us","number":"2254"},{"text":"and","number":"2532"},{"text":"Lord","number":"2962"},{"text":"saith","number":"3004"},{"text":"the Father","number":"3962"},{"text":"Philip","number":"5376"}],"30":[{"text":"the prince","number":"758"},{"text":"for","number":"1063"},{"text":"me","number":"1698"},{"text":"in","number":"1722"},{"text":"cometh","number":"2064"},{"text":"Hereafter","number":"2089"},{"text":"hath","number":"2192"},{"text":"and","number":"2532"},{"text":"world","number":"2889"},{"text":"I will","number":"2980"},{"text":"talk","number":"2980"},{"text":"with","number":"3326"},{"text":"nothing","number":"3762"},{"text":"not","number":"3765"},{"text":"much","number":"4183"},{"text":"of this","number":"5127"},{"text":"you","number":"5216"}],"11":[{"text":"sake","number":"846"},{"text":"the very","number":"846"},{"text":"for","number":"1223"},{"text":"I","number":"1473"},{"text":"or else","number":"1490"},{"text":"me","number":"1698"},{"text":"am in","number":"1722"},{"text":"in","number":"1722"},{"text":"works","number":"2041"},{"text":"and","number":"2532"},{"text":"me","number":"3427"},{"text":"me","number":"3427"},{"text":"that","number":"3754"},{"text":"the Father","number":"3962"},{"text":"the Father","number":"3962"},{"text":"Believe","number":"4100"},{"text":"believe","number":"4100"}],"22":[{"text":"unto him","number":"846"},{"text":"is it","number":"1096"},{"text":"manifest","number":"1718"},{"text":"unto us","number":"2254"},{"text":"Judas","number":"2455"},{"text":"Iscariot","number":"2469"},{"text":"and","number":"2532"},{"text":"unto the world","number":"2889"},{"text":"Lord","number":"2962"},{"text":"saith","number":"3004"},{"text":"thou wilt","number":"3195"},{"text":"that","number":"3754"},{"text":"not","number":"3756"},{"text":"not","number":"3780"},{"text":"thyself","number":"4572"},{"text":"how","number":"5101"}],"5":[{"text":"unto him","number":"846"},{"text":"can we","number":"1410"},{"text":"know","number":"1492"},{"text":"we know","number":"1492"},{"text":"Thomas","number":"2381"},{"text":"and","number":"2532"},{"text":"Lord","number":"2962"},{"text":"saith","number":"3004"},{"text":"the way","number":"3598"},{"text":"not","number":"3756"},{"text":"whither","number":"4226"},{"text":"how","number":"4459"},{"text":"thou goest","number":"5217"}],"9":[{"text":"unto him","number":"846"},{"text":"hast thou","number":"1097"},{"text":"known","number":"1097"},{"text":"then Shew","number":"1166"},{"text":"Have I been","number":"1510"},{"text":"me","number":"1691"},{"text":"us","number":"2254"},{"text":"Jesus","number":"2424"},{"text":"and","number":"2532"},{"text":"and yet","number":"2532"},{"text":"saith","number":"3004"},{"text":"sayest","number":"3004"},{"text":"me","number":"3165"},{"text":"with","number":"3326"},{"text":"hath seen","number":"3708"},{"text":"he that hath seen","number":"3708"},{"text":"not","number":"3756"},{"text":"the Father","number":"3962"},{"text":"the Father","number":"3962"},{"text":"how","number":"4459"},{"text":"thou","number":"4771"},{"text":"so long","number":"5118"},{"text":"you","number":"5216"},{"text":"Philip","number":"5376"},{"text":"time","number":"5550"}],"27":[{"text":"I leave","number":"863"},{"text":"let it be afraid","number":"1168"},{"text":"I give","number":"1325"},{"text":"give","number":"1325"},{"text":"giveth","number":"1325"},{"text":"I","number":"1473"},{"text":"Peace","number":"1515"},{"text":"peace","number":"1515"},{"text":"my","number":"1699"},{"text":"as","number":"2531"},{"text":"heart","number":"2588"},{"text":"the world","number":"2889"},{"text":"not","number":"3361"},{"text":"neither","number":"3366"},{"text":"not","number":"3756"},{"text":"Let","number":"5015"},{"text":"be troubled","number":"5015"},{"text":"unto you","number":"5213"},{"text":"unto you","number":"5213"},{"text":"with you","number":"5213"},{"text":"your","number":"5216"}],"18":[{"text":"I will","number":"863"},{"text":"leave","number":"863"},{"text":"I will come","number":"2064"},{"text":"comfortless","number":"3737"},{"text":"not","number":"3756"},{"text":"to","number":"4314"},{"text":"you","number":"5209"},{"text":"you","number":"5209"}],"29":[{"text":"it come to pass","number":"1096"},{"text":"it is come to pass","number":"1096"},{"text":"I have told","number":"2046"},{"text":"that","number":"2443"},{"text":"And","number":"2532"},{"text":"now","number":"3568"},{"text":"when","number":"3752"},{"text":"ye might believe","number":"4100"},{"text":"before","number":"4250"},{"text":"you","number":"5213"}],"20":[{"text":"shall know","number":"1097"},{"text":"I","number":"1473"},{"text":"that","number":"1565"},{"text":"me","number":"1698"},{"text":"At","number":"1722"},{"text":"am in","number":"1722"},{"text":"in","number":"1722"},{"text":"in","number":"1722"},{"text":"day","number":"2250"},{"text":"and I","number":"2504"},{"text":"and","number":"2532"},{"text":"my","number":"3450"},{"text":"that","number":"3754"},{"text":"Father","number":"3962"},{"text":"ye","number":"5210"},{"text":"ye","number":"5210"},{"text":"you","number":"5213"}],"19":[{"text":"but","number":"1161"},{"text":"I","number":"1473"},{"text":"Yet","number":"2089"},{"text":"more","number":"2089"},{"text":"live","number":"2198"},{"text":"shall live","number":"2198"},{"text":"see","number":"2334"},{"text":"seeth","number":"2334"},{"text":"also","number":"2532"},{"text":"and","number":"2532"},{"text":"the world","number":"2889"},{"text":"me","number":"3165"},{"text":"me","number":"3165"},{"text":"a little while","number":"3397"},{"text":"because","number":"3754"},{"text":"no","number":"3765"},{"text":"ye","number":"5210"},{"text":"ye","number":"5210"}],"3":[{"text":"if","number":"1437"},{"text":"I","number":"1473"},{"text":"am","number":"1510"},{"text":"myself","number":"1683"},{"text":"I will come","number":"2064"},{"text":"prepare","number":"2090"},{"text":"that","number":"2443"},{"text":"And","number":"2532"},{"text":"also","number":"2532"},{"text":"and","number":"2532"},{"text":"and","number":"2532"},{"text":"where","number":"3699"},{"text":"again","number":"3825"},{"text":"receive","number":"3880"},{"text":"I go","number":"4198"},{"text":"unto","number":"4314"},{"text":"a place","number":"5117"},{"text":"you","number":"5209"},{"text":"there ye","number":"5210"},{"text":"for you","number":"5213"},{"text":"may be","number":"5600"}],"4":[{"text":"I","number":"1473"},{"text":"ye know","number":"1492"},{"text":"ye know","number":"1492"},{"text":"And","number":"2532"},{"text":"and","number":"2532"},{"text":"the way","number":"3598"},{"text":"whither","number":"3699"},{"text":"go","number":"5217"}],"1":[{"text":"in","number":"1519"},{"text":"in","number":"1519"},{"text":"me","number":"1691"},{"text":"God","number":"2316"},{"text":"also","number":"2532"},{"text":"heart","number":"2588"},{"text":"not","number":"3361"},{"text":"believe","number":"4100"},{"text":"ye believe","number":"4100"},{"text":"Let","number":"5015"},{"text":"be troubled","number":"5015"},{"text":"your","number":"5216"}],"25":[{"text":"have I spoken","number":"2980"},{"text":"being yet present","number":"3306"},{"text":"with","number":"3844"},{"text":"These things","number":"5023"},{"text":"unto you","number":"5213"},{"text":"you","number":"5213"}]}