{"27":[{"text":"Thou art my father","number":"1"},{"text":"and to a stone","number":"68"},{"text":"Saying","number":"559"},{"text":"they will say","number":"559"},{"text":"Thou hast brought me forth","number":"3205"},{"text":"and save","number":"3467"},{"text":"to a stock","number":"6086"},{"text":"their back","number":"6203"},{"text":"but in the time","number":"6256"},{"text":"for they have turned","number":"6437"},{"text":"unto me and not their face","number":"6440"},{"text":"Arise","number":"6965"},{"text":"of their trouble","number":"7451"}],"5":[{"text":"have your fathers","number":"1"},{"text":"after","number":"310"},{"text":"Thus saith","number":"559"},{"text":"and are become vain","number":"1891"},{"text":"vanity","number":"1892"},{"text":"the LORD","number":"3068"},{"text":"from me and have walked","number":"3212"},{"text":"found","number":"4672"},{"text":"What iniquity","number":"5766"},{"text":"in me that they are gone far","number":"7368"}],"34":[{"text":"of the poor","number":"34"},{"text":"the blood","number":"1818"},{"text":"Also in thy skirts","number":"3671"},{"text":"it by secret search","number":"4290"},{"text":"I have not found","number":"4672"},{"text":"is found","number":"4672"},{"text":"of the souls","number":"5315"},{"text":"innocents","number":"5355"}],"6":[{"text":"and where no man","number":"120"},{"text":"that no man","number":"376"},{"text":"Neither said","number":"559"},{"text":"out of the land","number":"776"},{"text":"through a land","number":"776"},{"text":"through a land","number":"776"},{"text":"through a land","number":"776"},{"text":"they Where is the LORD","number":"3068"},{"text":"that led","number":"3212"},{"text":"dwelt","number":"3427"},{"text":"us through the wilderness","number":"4057"},{"text":"of Egypt","number":"4714"},{"text":"passed through","number":"5674"},{"text":"that brought us up","number":"5927"},{"text":"of deserts","number":"6160"},{"text":"of drought","number":"6723"},{"text":"and of the shadow of death","number":"6757"},{"text":"and of pits","number":"7745"}],"19":[{"text":"the Lord","number":"136"},{"text":"thy God","number":"430"},{"text":"thee know","number":"3045"},{"text":"the LORD","number":"3068"},{"text":"GOD","number":"3069"},{"text":"shall reprove","number":"3198"},{"text":"shall correct","number":"3256"},{"text":"thing and bitter","number":"4751"},{"text":"thee and thy backslidings","number":"4878"},{"text":"is not in thee saith","number":"5002"},{"text":"that thou hast forsaken","number":"5800"},{"text":"and that my fear","number":"6345"},{"text":"of hosts","number":"6635"},{"text":"therefore and see","number":"7200"},{"text":"Thine own wickedness","number":"7451"},{"text":"that it is an evil","number":"7451"}],"22":[{"text":"the Lord","number":"136"},{"text":"soap","number":"1287"},{"text":"GOD","number":"3069"},{"text":"For though thou wash","number":"3526"},{"text":"is marked","number":"3799"},{"text":"me saith","number":"5002"},{"text":"thee with nitre","number":"5427"},{"text":"yet thine iniquity","number":"5771"},{"text":"before","number":"6440"},{"text":"and take thee much","number":"7235"}],"25":[{"text":"no for I have loved","number":"157"},{"text":"and after","number":"310"},{"text":"but thou saidst","number":"559"},{"text":"and thy throat","number":"1627"},{"text":"strangers","number":"2114"},{"text":"There is no hope","number":"2976"},{"text":"from being unshod","number":"3182"},{"text":"them will I go","number":"3212"},{"text":"Withhold","number":"4513"},{"text":"from thirst","number":"6773"},{"text":"thy foot","number":"7272"}],"33":[{"text":"love","number":"160"},{"text":"to seek","number":"1245"},{"text":"thou thy way","number":"1870"},{"text":"thy ways","number":"1870"},{"text":"Why trimmest","number":"3190"},{"text":"therefore hast thou also taught","number":"3925"},{"text":"the wicked ones","number":"7451"}],"2":[{"text":"the love","number":"160"},{"text":"in the ears","number":"241"},{"text":"after","number":"310"},{"text":"Thus saith","number":"559"},{"text":"saying","number":"559"},{"text":"in a land","number":"776"},{"text":"Go","number":"1980"},{"text":"I remember","number":"2142"},{"text":"that was not sown","number":"2232"},{"text":"thee the kindness","number":"2617"},{"text":"the LORD","number":"3068"},{"text":"when thou wentest","number":"3212"},{"text":"of Jerusalem","number":"3389"},{"text":"of thine espousals","number":"3623"},{"text":"me in the wilderness","number":"4057"},{"text":"of thy youth","number":"5271"},{"text":"and cry","number":"7121"}],"24":[{"text":"at her pleasure","number":"185"},{"text":"all they that seek","number":"1245"},{"text":"themselves in her month","number":"2320"},{"text":"her will not weary","number":"3286"},{"text":"used","number":"3928"},{"text":"to the wilderness","number":"4057"},{"text":"they shall find","number":"4672"},{"text":"A wild ass","number":"6501"},{"text":"the wind","number":"7307"},{"text":"that snuffeth up","number":"7602"},{"text":"who can turn her away","number":"7725"},{"text":"in her occasion","number":"8385"}],"36":[{"text":"Why gaddest thou about","number":"235"},{"text":"of Assyria","number":"804"},{"text":"as thou wast ashamed","number":"954"},{"text":"thou also shalt be ashamed","number":"954"},{"text":"thy way","number":"1870"},{"text":"so much","number":"3966"},{"text":"of Egypt","number":"4714"},{"text":"to change","number":"8138"}],"23":[{"text":"after","number":"310"},{"text":"How canst thou say","number":"559"},{"text":"dromedary","number":"1072"},{"text":"Baalim","number":"1168"},{"text":"in the valley","number":"1516"},{"text":"her ways","number":"1870"},{"text":"thy way","number":"1870"},{"text":"I have not gone","number":"1980"},{"text":"I am not polluted","number":"2930"},{"text":"know","number":"3045"},{"text":"what thou hast done","number":"6213"},{"text":"thou art a swift","number":"7031"},{"text":"see","number":"7200"},{"text":"traversing","number":"8308"}],"8":[{"text":"after","number":"310"},{"text":"said","number":"559"},{"text":"by Baal","number":"1168"},{"text":"and walked","number":"1980"},{"text":"knew","number":"3045"},{"text":"not Where is the LORD","number":"3068"},{"text":"things that do not profit","number":"3276"},{"text":"The priests","number":"3548"},{"text":"prophesied","number":"5012"},{"text":"against me and the prophets","number":"5030"},{"text":"also transgressed","number":"6586"},{"text":"me not the pastors","number":"7462"},{"text":"the law","number":"8451"},{"text":"and they that handle","number":"8610"}],"10":[{"text":"the isles","number":"339"},{"text":"and consider","number":"995"},{"text":"of Chittim","number":"3794"},{"text":"diligently","number":"3966"},{"text":"For pass over","number":"5674"},{"text":"unto Kedar","number":"6938"},{"text":"and see","number":"7200"},{"text":"and see","number":"7200"},{"text":"and send","number":"7971"}],"3":[{"text":"all that devour","number":"398"},{"text":"him shall offend","number":"816"},{"text":"shall come","number":"935"},{"text":"the LORD","number":"3068"},{"text":"unto the LORD","number":"3068"},{"text":"Israel","number":"3478"},{"text":"upon them saith","number":"5002"},{"text":"was holiness","number":"6944"},{"text":"and the firstfruits","number":"7225"},{"text":"evil","number":"7451"},{"text":"of his increase","number":"8393"}],"30":[{"text":"hath devoured","number":"398"},{"text":"lion","number":"738"},{"text":"your children","number":"1121"},{"text":"your own sword","number":"2719"},{"text":"they received","number":"3947"},{"text":"no correction","number":"4148"},{"text":"your prophets","number":"5030"},{"text":"have I smitten","number":"5221"},{"text":"In vain","number":"7723"},{"text":"like a destroying","number":"7843"}],"7":[{"text":"to eat","number":"398"},{"text":"country","number":"776"},{"text":"my land","number":"776"},{"text":"And I brought","number":"935"},{"text":"thereof but when ye entered","number":"935"},{"text":"thereof and the goodness","number":"2898"},{"text":"ye defiled","number":"2930"},{"text":"you into a plentiful","number":"3759"},{"text":"mine heritage","number":"5159"},{"text":"the fruit","number":"6529"},{"text":"and made","number":"7760"},{"text":"an abomination","number":"8441"}],"28":[{"text":"But where are thy gods","number":"430"},{"text":"are thy gods","number":"430"},{"text":"O Judah","number":"3063"},{"text":"if they can save","number":"3467"},{"text":"for according to the number","number":"4557"},{"text":"of thy cities","number":"5892"},{"text":"that thou hast made","number":"6213"},{"text":"thee in the time","number":"6256"},{"text":"thee let them arise","number":"6965"},{"text":"of thy trouble","number":"7451"}],"11":[{"text":"their gods","number":"430"},{"text":"which are yet no gods","number":"430"},{"text":"Hath a nation","number":"1471"},{"text":"changed","number":"3235"},{"text":"for that which doth not profit","number":"3276"},{"text":"their glory","number":"3519"},{"text":"have changed","number":"4171"},{"text":"but my people","number":"5971"}],"17":[{"text":"thy God","number":"430"},{"text":"thee by the way","number":"1870"},{"text":"the LORD","number":"3068"},{"text":"he led","number":"3212"},{"text":"this unto thyself in that thou hast forsaken","number":"5800"},{"text":"Hast thou not procured","number":"6213"},{"text":"when","number":"6256"}],"35":[{"text":"Yet thou sayest","number":"559"},{"text":"with thee because thou sayest","number":"559"},{"text":"surely his anger","number":"639"},{"text":"I have not sinned","number":"2398"},{"text":"Because I am innocent","number":"5352"},{"text":"shall turn","number":"7725"},{"text":"from me Behold I will plead","number":"8199"}],"20":[{"text":"and thou saidst","number":"559"},{"text":"when upon every high","number":"1364"},{"text":"hill","number":"1389"},{"text":"playing the harlot","number":"2181"},{"text":"thy bands","number":"4147"},{"text":"and burst","number":"5423"},{"text":"I will not transgress","number":"5674"},{"text":"For of old time","number":"5769"},{"text":"thy yoke","number":"5923"},{"text":"tree","number":"6086"},{"text":"thou wanderest","number":"6808"},{"text":"and under every green","number":"7488"},{"text":"I have broken","number":"7665"}],"1":[{"text":"came to me saying","number":"559"},{"text":"Moreover the word","number":"1697"},{"text":"of the LORD","number":"3068"}],"31":[{"text":"wherefore say","number":"559"},{"text":"a land","number":"776"},{"text":"we will come","number":"935"},{"text":"ye the word","number":"1697"},{"text":"O generation","number":"1755"},{"text":"of the LORD","number":"3068"},{"text":"unto Israel","number":"3478"},{"text":"of darkness","number":"3991"},{"text":"Have I been a wilderness","number":"4057"},{"text":"my people","number":"5971"},{"text":"see","number":"7200"},{"text":"We are lords","number":"7300"}],"21":[{"text":"wholly a right","number":"571"},{"text":"vine","number":"1612"},{"text":"how then art thou turned","number":"2015"},{"text":"seed","number":"2233"},{"text":"Yet I had planted","number":"5193"},{"text":"of a strange","number":"5237"},{"text":"into the degenerate plant","number":"5494"},{"text":"thee a noble vine","number":"8321"}],"15":[{"text":"his land","number":"776"},{"text":"are burned","number":"3341"},{"text":"without inhabitant","number":"3427"},{"text":"The young lions","number":"3715"},{"text":"upon him and yelled","number":"5414"},{"text":"his cities","number":"5892"},{"text":"roared","number":"7580"},{"text":"and they made","number":"7896"},{"text":"waste","number":"8047"}],"18":[{"text":"of Assyria","number":"804"},{"text":"And now what hast thou to do in the way","number":"1870"},{"text":"or what hast thou to do in the way","number":"1870"},{"text":"the waters","number":"4325"},{"text":"the waters","number":"4325"},{"text":"of Egypt","number":"4714"},{"text":"of the river","number":"5104"},{"text":"of Sihor","number":"7883"},{"text":"to drink","number":"8354"},{"text":"to drink","number":"8354"}],"13":[{"text":"cisterns","number":"877"},{"text":"cisterns","number":"877"},{"text":"of living","number":"2416"},{"text":"and hewed them out","number":"2672"},{"text":"that can hold","number":"3557"},{"text":"no water","number":"4325"},{"text":"waters","number":"4325"},{"text":"me the fountain","number":"4726"},{"text":"they have forsaken","number":"5800"},{"text":"For my people","number":"5971"},{"text":"have committed","number":"6213"},{"text":"evils","number":"7451"},{"text":"broken","number":"7665"},{"text":"two","number":"8147"}],"14":[{"text":"is he spoiled","number":"957"},{"text":"is he a homeborn","number":"1004"},{"text":"Is Israel","number":"3478"},{"text":"slave why","number":"4069"},{"text":"a servant","number":"5650"}],"4":[{"text":"O house","number":"1004"},{"text":"of the house","number":"1004"},{"text":"ye the word","number":"1697"},{"text":"of the LORD","number":"3068"},{"text":"of Jacob","number":"3290"},{"text":"of Israel","number":"3478"},{"text":"and all the families","number":"4940"},{"text":"Hear","number":"8085"}],"26":[{"text":"so is the house","number":"1004"},{"text":"is ashamed","number":"1322"},{"text":"As the thief","number":"1590"},{"text":"ashamed","number":"3001"},{"text":"of Israel","number":"3478"},{"text":"and their priests","number":"3548"},{"text":"they their kings","number":"4428"},{"text":"when he is found","number":"4672"},{"text":"and their prophets","number":"5030"},{"text":"their princes","number":"8269"}],"16":[{"text":"Also the children","number":"1121"},{"text":"of Noph","number":"5297"},{"text":"the crown of thy head","number":"6936"},{"text":"have broken","number":"7462"},{"text":"and Tahapanes","number":"8471"}],"9":[{"text":"and with your children's","number":"1121"},{"text":"children","number":"1121"},{"text":"the LORD","number":"3068"},{"text":"with you saith","number":"5002"},{"text":"Wherefore I will yet plead","number":"7378"},{"text":"will I plead","number":"7378"}],"32":[{"text":"Can a maid","number":"1330"},{"text":"me days","number":"3117"},{"text":"or a bride","number":"3618"},{"text":"without number","number":"4557"},{"text":"her ornaments","number":"5716"},{"text":"yet my people","number":"5971"},{"text":"her attire","number":"7196"},{"text":"forget","number":"7911"},{"text":"have forgotten","number":"7911"}],"12":[{"text":"desolate","number":"2717"},{"text":"the LORD","number":"3068"},{"text":"be ye very","number":"3966"},{"text":"saith","number":"5002"},{"text":"O ye heavens","number":"8064"},{"text":"Be astonished","number":"8074"},{"text":"at this and be horribly afraid","number":"8175"}],"37":[{"text":"from him and thine hands","number":"3027"},{"text":"for the LORD","number":"3068"},{"text":"Yea thou shalt go forth","number":"3318"},{"text":"hath rejected","number":"3988"},{"text":"thy confidences","number":"4009"},{"text":"and thou shalt not prosper","number":"6743"},{"text":"upon thine head","number":"7218"}],"29":[{"text":"the LORD","number":"3068"},{"text":"against me saith","number":"5002"},{"text":"with me ye all have transgressed","number":"6586"},{"text":"Wherefore will ye plead","number":"7378"}]}