{"24":[{"text":"his father","number":"1"},{"text":"both Ajah","number":"345"},{"text":"And these are the children","number":"1121"},{"text":"the asses","number":"2543"},{"text":"the mules","number":"3222"},{"text":"in the wilderness","number":"4057"},{"text":"that found","number":"4672"},{"text":"and Anah","number":"6034"},{"text":"this was that Anah","number":"6034"},{"text":"of Zibeon","number":"6649"},{"text":"of Zibeon","number":"6649"},{"text":"as he fed","number":"7462"}],"43":[{"text":"the father","number":"1"},{"text":"of Edom","number":"123"},{"text":"of the Edomites","number":"123"},{"text":"of their possession","number":"272"},{"text":"Duke","number":"441"},{"text":"duke","number":"441"},{"text":"these be the dukes","number":"441"},{"text":"in the land","number":"776"},{"text":"Magdiel","number":"4025"},{"text":"according to their habitations","number":"4186"},{"text":"Iram","number":"5902"},{"text":"he is Esau","number":"6215"}],"9":[{"text":"the father","number":"1"},{"text":"of the Edomites","number":"123"},{"text":"in mount","number":"2022"},{"text":"of Esau","number":"6215"},{"text":"Seir","number":"8165"},{"text":"And these are the generations","number":"8435"}],"32":[{"text":"in Edom","number":"123"},{"text":"And Bela","number":"1106"},{"text":"the son","number":"1121"},{"text":"of Beor","number":"1160"},{"text":"was Dinhabah","number":"1838"},{"text":"reigned","number":"4427"},{"text":"of his city","number":"5892"},{"text":"and the name","number":"8034"}],"8":[{"text":"is Edom","number":"123"},{"text":"in mount","number":"2022"},{"text":"Thus dwelt","number":"3427"},{"text":"Esau","number":"6215"},{"text":"Esau","number":"6215"},{"text":"Seir","number":"8165"}],"16":[{"text":"of Edom","number":"123"},{"text":"Duke","number":"441"},{"text":"and duke","number":"441"},{"text":"duke","number":"441"},{"text":"these are the dukes","number":"441"},{"text":"that came of Eliphaz","number":"464"},{"text":"in the land","number":"776"},{"text":"these were the sons","number":"1121"},{"text":"Gatam","number":"1609"},{"text":"of Adah","number":"5711"},{"text":"Amalek","number":"6002"},{"text":"Korah","number":"7141"}],"17":[{"text":"of Edom","number":"123"},{"text":"duke","number":"441"},{"text":"duke","number":"441"},{"text":"duke","number":"441"},{"text":"duke","number":"441"},{"text":"these are the dukes","number":"441"},{"text":"in the land","number":"776"},{"text":"wife","number":"802"},{"text":"And these are the sons","number":"1121"},{"text":"son","number":"1121"},{"text":"these are the sons","number":"1121"},{"text":"of Bashemath","number":"1315"},{"text":"Zerah","number":"2226"},{"text":"Mizzah","number":"4199"},{"text":"Nahath","number":"5184"},{"text":"Esau's","number":"6215"},{"text":"Esau's","number":"6215"},{"text":"of Reuel","number":"7467"},{"text":"that came of Reuel","number":"7467"},{"text":"Shammah","number":"8048"}],"21":[{"text":"of Edom","number":"123"},{"text":"these are the dukes","number":"441"},{"text":"and Ezer","number":"687"},{"text":"in the land","number":"776"},{"text":"the children","number":"1121"},{"text":"And Dishon","number":"1787"},{"text":"and Dishan","number":"1789"},{"text":"of the Horites","number":"2752"},{"text":"of Seir","number":"8165"}],"31":[{"text":"of Edom","number":"123"},{"text":"in the land","number":"776"},{"text":"over the children","number":"1121"},{"text":"of Israel","number":"3478"},{"text":"that reigned","number":"4427"},{"text":"there reigned","number":"4427"},{"text":"And these are the kings","number":"4428"},{"text":"any king","number":"4428"},{"text":"before","number":"6440"}],"1":[{"text":"who is Edom","number":"123"},{"text":"of Esau","number":"6215"},{"text":"Now these are the generations","number":"8435"}],"19":[{"text":"who is Edom","number":"123"},{"text":"and these are their dukes","number":"441"},{"text":"These are the sons","number":"1121"},{"text":"of Esau","number":"6215"}],"41":[{"text":"Aholibamah","number":"173"},{"text":"Elah","number":"425"},{"text":"Duke","number":"441"},{"text":"duke","number":"441"},{"text":"duke","number":"441"},{"text":"Pinon","number":"6373"}],"5":[{"text":"And Aholibamah","number":"173"},{"text":"unto him in the land","number":"776"},{"text":"these are the sons","number":"1121"},{"text":"bare","number":"3205"},{"text":"which were born","number":"3205"},{"text":"Jeush","number":"3274"},{"text":"and Jaalam","number":"3281"},{"text":"of Canaan","number":"3667"},{"text":"of Esau","number":"6215"},{"text":"and Korah","number":"7141"}],"2":[{"text":"and Aholibamah","number":"173"},{"text":"of Elon","number":"356"},{"text":"his wives","number":"802"},{"text":"of the daughters","number":"1323"},{"text":"the daughter","number":"1323"},{"text":"the daughter","number":"1323"},{"text":"the daughter","number":"1323"},{"text":"the Hivite","number":"2340"},{"text":"the Hittite","number":"2850"},{"text":"of Canaan","number":"3667"},{"text":"took","number":"3947"},{"text":"Adah","number":"5711"},{"text":"of Anah","number":"6034"},{"text":"Esau","number":"6215"},{"text":"of Zibeon","number":"6649"}],"25":[{"text":"and Aholibamah","number":"173"},{"text":"And the children","number":"1121"},{"text":"the daughter","number":"1323"},{"text":"were these Dishon","number":"1787"},{"text":"of Anah","number":"6034"},{"text":"of Anah","number":"6034"}],"14":[{"text":"of Aholibamah","number":"173"},{"text":"wife","number":"802"},{"text":"And these were the sons","number":"1121"},{"text":"the daughter","number":"1323"},{"text":"the daughter","number":"1323"},{"text":"and she bare","number":"3205"},{"text":"Jeush","number":"3274"},{"text":"and Jaalam","number":"3281"},{"text":"of Anah","number":"6034"},{"text":"Esau's","number":"6215"},{"text":"to Esau","number":"6215"},{"text":"of Zibeon","number":"6649"},{"text":"and Korah","number":"7141"}],"18":[{"text":"of Aholibamah","number":"173"},{"text":"that came of Aholibamah","number":"173"},{"text":"duke","number":"441"},{"text":"duke","number":"441"},{"text":"duke","number":"441"},{"text":"these were the dukes","number":"441"},{"text":"wife","number":"802"},{"text":"wife","number":"802"},{"text":"And these are the sons","number":"1121"},{"text":"the daughter","number":"1323"},{"text":"Jeush","number":"3266"},{"text":"Jaalam","number":"3281"},{"text":"of Anah","number":"6034"},{"text":"Esau's","number":"6215"},{"text":"Esau's","number":"6215"},{"text":"Korah","number":"7141"}],"11":[{"text":"Omar","number":"201"},{"text":"of Eliphaz","number":"464"},{"text":"And the sons","number":"1121"},{"text":"and Gatam","number":"1609"},{"text":"Zepho","number":"6825"},{"text":"and Kenaz","number":"7073"},{"text":"were Teman","number":"8487"}],"15":[{"text":"Omar","number":"201"},{"text":"These were dukes","number":"441"},{"text":"duke","number":"441"},{"text":"duke","number":"441"},{"text":"duke","number":"441"},{"text":"duke","number":"441"},{"text":"of Eliphaz","number":"464"},{"text":"the firstborn","number":"1060"},{"text":"of the sons","number":"1121"},{"text":"the sons","number":"1121"},{"text":"of Esau","number":"6215"},{"text":"son of Esau","number":"6215"},{"text":"Zepho","number":"6825"},{"text":"Kenaz","number":"7073"},{"text":"Teman","number":"8487"}],"23":[{"text":"and Onam","number":"208"},{"text":"And the children","number":"1121"},{"text":"and Manahath","number":"4506"},{"text":"and Ebal","number":"5858"},{"text":"were these Alvan","number":"5935"},{"text":"of Shobal","number":"7732"},{"text":"Shepho","number":"8195"}],"6":[{"text":"of his brother","number":"251"},{"text":"in the land","number":"776"},{"text":"into the country","number":"776"},{"text":"his wives","number":"802"},{"text":"and all his beasts","number":"929"},{"text":"of his house","number":"1004"},{"text":"and his sons","number":"1121"},{"text":"and his daughters","number":"1323"},{"text":"and went","number":"3212"},{"text":"Jacob","number":"3290"},{"text":"of Canaan","number":"3667"},{"text":"took","number":"3947"},{"text":"and his cattle","number":"4735"},{"text":"and all the persons","number":"5315"},{"text":"And Esau","number":"6215"},{"text":"from the face","number":"6440"},{"text":"and all his substance","number":"7075"},{"text":"which he had got","number":"7408"}],"22":[{"text":"sister","number":"269"},{"text":"And the children","number":"1121"},{"text":"and Hemam","number":"1967"},{"text":"were Hori","number":"2753"},{"text":"and Lotan's","number":"3877"},{"text":"of Lotan","number":"3877"},{"text":"was Timna","number":"8555"}],"3":[{"text":"sister","number":"269"},{"text":"And Bashemath","number":"1315"},{"text":"daughter","number":"1323"},{"text":"Ishmael's","number":"3458"},{"text":"of Nebajoth","number":"5032"}],"30":[{"text":"Duke","number":"441"},{"text":"among their dukes","number":"441"},{"text":"duke","number":"441"},{"text":"duke","number":"441"},{"text":"these are the dukes","number":"441"},{"text":"Ezer","number":"687"},{"text":"in the land","number":"776"},{"text":"Dishon","number":"1787"},{"text":"Dishan","number":"1789"},{"text":"that came of Hori","number":"2753"},{"text":"of Seir","number":"8165"}],"42":[{"text":"Duke","number":"441"},{"text":"duke","number":"441"},{"text":"duke","number":"441"},{"text":"Mibzar","number":"4014"},{"text":"Kenaz","number":"7073"},{"text":"Teman","number":"8487"}],"29":[{"text":"These are the dukes","number":"441"},{"text":"duke","number":"441"},{"text":"duke","number":"441"},{"text":"duke","number":"441"},{"text":"duke","number":"441"},{"text":"that came of the Horites","number":"2752"},{"text":"Lotan","number":"3877"},{"text":"Anah","number":"6034"},{"text":"Zibeon","number":"6649"},{"text":"Shobal","number":"7732"}],"40":[{"text":"duke","number":"441"},{"text":"duke","number":"441"},{"text":"duke","number":"441"},{"text":"of the dukes","number":"441"},{"text":"Jetheth","number":"3509"},{"text":"after their places","number":"4725"},{"text":"according to their families","number":"4940"},{"text":"Alvah","number":"5933"},{"text":"that came of Esau","number":"6215"},{"text":"And these are the names","number":"8034"},{"text":"by their names","number":"8034"},{"text":"Timnah","number":"8555"}],"10":[{"text":"Eliphaz","number":"464"},{"text":"the wife","number":"802"},{"text":"the wife","number":"802"},{"text":"sons","number":"1121"},{"text":"the son","number":"1121"},{"text":"the son","number":"1121"},{"text":"of Bashemath","number":"1315"},{"text":"of Adah","number":"5711"},{"text":"of Esau","number":"6215"},{"text":"of Esau","number":"6215"},{"text":"of Esau's","number":"6215"},{"text":"Reuel","number":"7467"},{"text":"These are the names","number":"8034"}],"4":[{"text":"Eliphaz","number":"464"},{"text":"and Bashemath","number":"1315"},{"text":"bare","number":"3205"},{"text":"bare","number":"3205"},{"text":"And Adah","number":"5711"},{"text":"to Esau","number":"6215"},{"text":"Reuel","number":"7467"}],"12":[{"text":"to Eliphaz","number":"464"},{"text":"to Eliphaz","number":"464"},{"text":"wife","number":"802"},{"text":"son","number":"1121"},{"text":"these were the sons","number":"1121"},{"text":"and she bare","number":"3205"},{"text":"of Adah","number":"5711"},{"text":"Amalek","number":"6002"},{"text":"Esau's","number":"6215"},{"text":"Esau's","number":"6215"},{"text":"was concubine","number":"6370"},{"text":"And Timna","number":"8555"}],"27":[{"text":"of Ezer","number":"687"},{"text":"are these Bilhan","number":"1092"},{"text":"The children","number":"1121"},{"text":"and Zaavan","number":"2190"},{"text":"and Akan","number":"6130"}],"28":[{"text":"and Aran","number":"765"},{"text":"The children","number":"1121"},{"text":"of Dishan","number":"1789"},{"text":"are these Uz","number":"5780"}],"7":[{"text":"and the land","number":"776"},{"text":"together","number":"3162"},{"text":"could","number":"3201"},{"text":"than that they might dwell","number":"3427"},{"text":"wherein they were strangers","number":"4033"},{"text":"of their cattle","number":"4735"},{"text":"not bear","number":"5375"},{"text":"them because","number":"6440"},{"text":"were more","number":"7227"},{"text":"For their riches","number":"7399"}],"34":[{"text":"of the land","number":"776"},{"text":"and Husham","number":"2367"},{"text":"And Jobab","number":"3103"},{"text":"died","number":"4191"},{"text":"reigned","number":"4427"},{"text":"of Temani","number":"8489"}],"20":[{"text":"the land","number":"776"},{"text":"These are the sons","number":"1121"},{"text":"the Horite","number":"2752"},{"text":"who inhabited","number":"3427"},{"text":"Lotan","number":"3877"},{"text":"and Anah","number":"6034"},{"text":"and Zibeon","number":"6649"},{"text":"and Shobal","number":"7732"},{"text":"of Seir","number":"8165"}],"26":[{"text":"and Eshban","number":"790"},{"text":"And these are the children","number":"1121"},{"text":"of Dishon","number":"1787"},{"text":"Hemdan","number":"2533"},{"text":"and Ithran","number":"3506"},{"text":"and Cheran","number":"3763"}],"39":[{"text":"and his wife's","number":"802"},{"text":"the son","number":"1121"},{"text":"And Baalhanan","number":"1177"},{"text":"the daughter","number":"1323"},{"text":"the daughter","number":"1323"},{"text":"and Hadar","number":"1924"},{"text":"was Mehetabel","number":"4105"},{"text":"died","number":"4191"},{"text":"of Matred","number":"4308"},{"text":"of Mezahab","number":"4314"},{"text":"reigned","number":"4427"},{"text":"of his city","number":"5892"},{"text":"of Achbor","number":"5907"},{"text":"was Pau","number":"6464"},{"text":"in his stead and the name","number":"8034"},{"text":"name","number":"8034"}],"13":[{"text":"wife","number":"802"},{"text":"And these are the sons","number":"1121"},{"text":"these were the sons","number":"1121"},{"text":"of Bashemath","number":"1315"},{"text":"and Zerah","number":"2226"},{"text":"and Mizzah","number":"4199"},{"text":"Nahath","number":"5184"},{"text":"Esau's","number":"6215"},{"text":"of Reuel","number":"7467"},{"text":"Shammah","number":"8048"}],"35":[{"text":"of Bedad","number":"911"},{"text":"the son","number":"1121"},{"text":"and Hadad","number":"1908"},{"text":"And Husham","number":"2367"},{"text":"Midian","number":"4080"},{"text":"of Moab","number":"4124"},{"text":"died","number":"4191"},{"text":"reigned","number":"4427"},{"text":"who smote","number":"5221"},{"text":"was Avith","number":"5762"},{"text":"of his city","number":"5892"},{"text":"in the field","number":"7704"},{"text":"in his stead and the name","number":"8034"}],"33":[{"text":"And Bela","number":"1106"},{"text":"the son","number":"1121"},{"text":"of Bozrah","number":"1224"},{"text":"of Zerah","number":"2226"},{"text":"and Jobab","number":"3103"},{"text":"died","number":"4191"},{"text":"reigned","number":"4427"}],"38":[{"text":"the son","number":"1121"},{"text":"and Baalhanan","number":"1177"},{"text":"died","number":"4191"},{"text":"reigned","number":"4427"},{"text":"of Achbor","number":"5907"},{"text":"And Saul","number":"7586"}],"36":[{"text":"And Hadad","number":"1908"},{"text":"died","number":"4191"},{"text":"reigned","number":"4427"},{"text":"of Masrekah","number":"4957"},{"text":"and Samlah","number":"8072"}],"37":[{"text":"died","number":"4191"},{"text":"reigned","number":"4427"},{"text":"by the river","number":"5104"},{"text":"of Rehoboth","number":"7344"},{"text":"and Saul","number":"7586"},{"text":"And Samlah","number":"8072"}]}