{"21":[{"text":"and every man","number":"120"},{"text":"upon the earth","number":"776"},{"text":"upon the earth","number":"776"},{"text":"and of cattle","number":"929"},{"text":"And all flesh","number":"1320"},{"text":"died","number":"1478"},{"text":"and of beast","number":"2416"},{"text":"both of fowl","number":"5775"},{"text":"that moved","number":"7430"},{"text":"that creepeth","number":"8317"},{"text":"and of every creeping thing","number":"8318"}],"23":[{"text":"both man","number":"120"},{"text":"of the ground","number":"127"},{"text":"only","number":"389"},{"text":"from the earth","number":"776"},{"text":"alive and they that","number":"834"},{"text":"and cattle","number":"929"},{"text":"And every living substance","number":"3351"},{"text":"and they were destroyed","number":"4229"},{"text":"was destroyed","number":"4229"},{"text":"and Noah","number":"5146"},{"text":"and the fowl","number":"5775"},{"text":"which was upon the face","number":"6440"},{"text":"and the creeping things","number":"7431"},{"text":"remained","number":"7604"},{"text":"of the heaven","number":"8064"},{"text":"were with him in the ark","number":"8392"}],"4":[{"text":"of the earth","number":"127"},{"text":"and forty","number":"705"},{"text":"forty","number":"705"},{"text":"upon the earth","number":"776"},{"text":"days","number":"3117"},{"text":"days","number":"3117"},{"text":"living substance","number":"3351"},{"text":"and every","number":"3605"},{"text":"nights","number":"3915"},{"text":"will I destroy","number":"4229"},{"text":"and I will cause it to rain","number":"4305"},{"text":"For yet","number":"5750"},{"text":"from off","number":"5921"},{"text":"that I have made","number":"6213"},{"text":"the face","number":"6440"},{"text":"seven","number":"7651"}],"8":[{"text":"upon the earth","number":"127"},{"text":"and of beasts","number":"929"},{"text":"beasts","number":"929"},{"text":"Of clean","number":"2889"},{"text":"that are not clean","number":"2889"},{"text":"and of fowls","number":"5775"},{"text":"and of every thing that creepeth","number":"7430"}],"2":[{"text":"the male","number":"376"},{"text":"the male","number":"376"},{"text":"and his female","number":"802"},{"text":"and his female","number":"802"},{"text":"and of beasts","number":"929"},{"text":"beast","number":"929"},{"text":"Of every clean","number":"2889"},{"text":"that are not clean","number":"2889"},{"text":"thou shalt take","number":"3947"},{"text":"to thee by sevens","number":"7651"},{"text":"by two","number":"8147"}],"9":[{"text":"God","number":"430"},{"text":"as","number":"834"},{"text":"There went in","number":"935"},{"text":"the male","number":"2145"},{"text":"Noah","number":"5146"},{"text":"unto Noah","number":"5146"},{"text":"and the female","number":"5347"},{"text":"had commanded","number":"6680"},{"text":"and two","number":"8147"},{"text":"two","number":"8147"},{"text":"into the ark","number":"8392"}],"16":[{"text":"as God","number":"430"},{"text":"And they that went in","number":"935"},{"text":"went in","number":"935"},{"text":"of all flesh","number":"1320"},{"text":"male","number":"2145"},{"text":"him and the LORD","number":"3068"},{"text":"and female","number":"5347"},{"text":"shut him in","number":"5462"},{"text":"had commanded","number":"6680"}],"20":[{"text":"cubits","number":"520"},{"text":"prevail","number":"1396"},{"text":"and the mountains","number":"2022"},{"text":"were covered","number":"3680"},{"text":"did the waters","number":"4325"},{"text":"upward","number":"4605"},{"text":"Fifteen","number":"6240"}],"1":[{"text":"said","number":"559"},{"text":"Come","number":"935"},{"text":"thou and all thy house","number":"1004"},{"text":"generation","number":"1755"},{"text":"in this","number":"2088"},{"text":"And the LORD","number":"3068"},{"text":"unto Noah","number":"5146"},{"text":"before me","number":"6440"},{"text":"righteous","number":"6662"},{"text":"for thee have I seen","number":"7200"},{"text":"into the ark","number":"8392"}],"22":[{"text":"All in whose nostrils","number":"639"},{"text":"of life","number":"2416"},{"text":"of all that was in the dry","number":"2724"},{"text":"land died","number":"4191"},{"text":"was the breath","number":"5397"}],"11":[{"text":"and the windows","number":"699"},{"text":"broken up","number":"1234"},{"text":"the same","number":"2088"},{"text":"month","number":"2320"},{"text":"of the month","number":"2320"},{"text":"life","number":"2416"},{"text":"day","number":"3117"},{"text":"day","number":"3117"},{"text":"hundredth","number":"3967"},{"text":"were all the fountains","number":"4599"},{"text":"of Noah's","number":"5146"},{"text":"were opened","number":"6605"},{"text":"of the great","number":"7227"},{"text":"the seventeenth","number":"7651"},{"text":"of heaven","number":"8064"},{"text":"In","number":"8141"},{"text":"year","number":"8141"},{"text":"in the second","number":"8145"},{"text":"the six","number":"8337"},{"text":"deep","number":"8415"}],"12":[{"text":"and forty","number":"705"},{"text":"forty","number":"705"},{"text":"was upon the earth","number":"776"},{"text":"And the rain","number":"1653"},{"text":"days","number":"3117"},{"text":"nights","number":"3915"}],"17":[{"text":"was forty","number":"705"},{"text":"above the earth","number":"776"},{"text":"upon the earth","number":"776"},{"text":"days","number":"3117"},{"text":"And the flood","number":"3999"},{"text":"and the waters","number":"4325"},{"text":"and bare up","number":"5375"},{"text":"increased","number":"7235"},{"text":"and it was lift up","number":"7311"},{"text":"the ark","number":"8392"}],"3":[{"text":"of all the earth","number":"776"},{"text":"the male","number":"2145"},{"text":"seed","number":"2233"},{"text":"alive","number":"2421"},{"text":"to keep","number":"2421"},{"text":"and the female","number":"5347"},{"text":"Of fowls","number":"5775"},{"text":"upon the face","number":"6440"},{"text":"by sevens","number":"7651"},{"text":"also of the air","number":"8064"}],"14":[{"text":"upon the earth","number":"776"},{"text":"and all the cattle","number":"929"},{"text":"They","number":"1992"},{"text":"and every beast","number":"2416"},{"text":"of every sort","number":"3671"},{"text":"after his kind","number":"4327"},{"text":"after his kind","number":"4327"},{"text":"after his kind","number":"4327"},{"text":"after their kind","number":"4327"},{"text":"and every fowl","number":"5775"},{"text":"every bird","number":"6833"},{"text":"that creepeth","number":"7430"},{"text":"and every creeping thing","number":"7431"}],"18":[{"text":"upon the earth","number":"776"},{"text":"prevailed","number":"1396"},{"text":"went","number":"3212"},{"text":"greatly","number":"3966"},{"text":"And the waters","number":"4325"},{"text":"of the waters","number":"4325"},{"text":"upon the face","number":"6440"},{"text":"and were increased","number":"7235"},{"text":"and the ark","number":"8392"}],"19":[{"text":"upon the earth","number":"776"},{"text":"and all the high","number":"1364"},{"text":"prevailed","number":"1396"},{"text":"hills","number":"2022"},{"text":"were covered","number":"3680"},{"text":"exceedingly","number":"3966"},{"text":"And the waters","number":"4325"},{"text":"the whole heaven","number":"8064"},{"text":"that were under","number":"8478"}],"24":[{"text":"upon the earth","number":"776"},{"text":"prevailed","number":"1396"},{"text":"and fifty","number":"2572"},{"text":"days","number":"3117"},{"text":"an hundred","number":"3967"},{"text":"And the waters","number":"4325"}],"6":[{"text":"was upon the earth","number":"776"},{"text":"old","number":"1121"},{"text":"hundred","number":"3967"},{"text":"when the flood","number":"3999"},{"text":"of waters","number":"4325"},{"text":"And Noah","number":"5146"},{"text":"years","number":"8141"},{"text":"was six","number":"8337"}],"10":[{"text":"were upon the earth","number":"776"},{"text":"days","number":"3117"},{"text":"of the flood","number":"3999"},{"text":"that the waters","number":"4325"},{"text":"And it came to pass after seven","number":"7651"}],"7":[{"text":"and his wife","number":"802"},{"text":"wives","number":"802"},{"text":"went in","number":"935"},{"text":"and his sons","number":"1121"},{"text":"and his sons","number":"1121"},{"text":"of the flood","number":"3999"},{"text":"the waters","number":"4325"},{"text":"And Noah","number":"5146"},{"text":"because of","number":"6440"},{"text":"with him into the ark","number":"8392"}],"13":[{"text":"wife","number":"802"},{"text":"wives","number":"802"},{"text":"entered","number":"935"},{"text":"of his sons","number":"1121"},{"text":"the sons","number":"1121"},{"text":"and Ham","number":"2526"},{"text":"day","number":"3117"},{"text":"and Japheth","number":"3315"},{"text":"Noah","number":"5146"},{"text":"and Noah's","number":"5146"},{"text":"of Noah","number":"5146"},{"text":"In the selfsame","number":"6106"},{"text":"and the three","number":"7969"},{"text":"and Shem","number":"8035"},{"text":"with them into the ark","number":"8392"}],"15":[{"text":"wherein","number":"834"},{"text":"And they went in","number":"935"},{"text":"of all flesh","number":"1320"},{"text":"of life","number":"2416"},{"text":"unto Noah","number":"5146"},{"text":"is the breath","number":"7307"},{"text":"and two","number":"8147"},{"text":"two","number":"8147"},{"text":"into the ark","number":"8392"}],"5":[{"text":"according unto all that the LORD","number":"3068"},{"text":"And Noah","number":"5146"},{"text":"did","number":"6213"},{"text":"commanded","number":"6680"}]}